[
  {
    "id": 1,
    "text": {
      "ar": "الْقَيُّومُ",
      "en": "the Sustainer of all that exists",
      "tr": "l-qayūmu",
      "ru": "Сущего!"
    },
    "aud": "003_002_007",
    "img": "/img/book.png"
  },
  {
    "id": 2,
    "text": {
      "ar": "يُصَوِّرُكُمْ",
      "en": "shapes you",
      "tr": "yuṣawwirukum",
      "ru": "придаёт вам форму"
    },
    "aud": "003_006_003",
    "img": "/img/book.png"
  },
  {
    "id": 3,
    "text": {
      "ar": "مُحْكَمَاتٌ",
      "en": "absolutely clear",
      "tr": "muḥ'kamātun",
      "ru": "с однозначным смыслом,"
    },
    "aud": "003_007_008",
    "img": "/img/book.png"
  },
  {
    "id": 4,
    "text": {
      "ar": "وَأُخَرُ",
      "en": "and others",
      "tr": "wa-ukharu",
      "ru": "А другие –"
    },
    "aud": "003_007_012",
    "img": "/img/book.png"
  },
  {
    "id": 5,
    "text": {
      "ar": "مُتَشَابِهَاتٌ",
      "en": "(are) allegorical",
      "tr": "mutashābihātun",
      "ru": "с многозначным смыслом."
    },
    "aud": "003_007_013",
    "img": "/img/book.png"
  },
  {
    "id": 6,
    "text": {
      "ar": "زَيْغٌ",
      "en": "(is) perversity",
      "tr": "zayghun",
      "ru": "уклонение,"
    },
    "aud": "003_007_018",
    "img": "/img/book.png"
  },
  {
    "id": 7,
    "text": {
      "ar": "تَشَابَهَ",
      "en": "(is) allegorical",
      "tr": "tashābaha",
      "ru": "является многозначным"
    },
    "aud": "003_007_021",
    "img": "/img/book.png"
  },
  {
    "id": 8,
    "text": {
      "ar": "تَأْوِيلِهِ",
      "en": "its interpretation",
      "tr": "tawīlihi",
      "ru": "толкования этого,"
    },
    "aud": "003_007_026",
    "img": "/img/book.png"
  },
  {
    "id": 9,
    "text": {
      "ar": "وَالرَّاسِخُونَ",
      "en": "And those firm",
      "tr": "wal-rāsikhūna",
      "ru": "А твердые"
    },
    "aud": "003_007_032",
    "img": "/img/book.png"
  },
  {
    "id": 10,
    "text": {
      "ar": "تُزِغْ",
      "en": "deviate",
      "tr": "tuzigh",
      "ru": "уклоняй"
    },
    "aud": "003_008_003",
    "img": "/img/book.png"
  },
  {
    "id": 11,
    "text": {
      "ar": "قُلُوبَنَا",
      "en": "our hearts",
      "tr": "qulūbanā",
      "ru": "наши сердца"
    },
    "aud": "003_008_004",
    "img": "/img/book.png"
  },
  {
    "id": 12,
    "text": {
      "ar": "هَدَيْتَنَا",
      "en": "You (have) guided us",
      "tr": "hadaytanā",
      "ru": "наставил Ты нас (на истинный путь)"
    },
    "aud": "003_008_007",
    "img": "/img/book.png"
  },
  {
    "id": 13,
    "text": {
      "ar": "وَقُودُ",
      "en": "(the) fuel",
      "tr": "waqūdu",
      "ru": "растопка"
    },
    "aud": "003_010_015",
    "img": "/img/book.png"
  },
  {
    "id": 14,
    "text": {
      "ar": "سَتُغْلَبُونَ",
      "en": "You will be overcome",
      "tr": "satugh'labūna",
      "ru": "«Вскоре вы будете побеждены"
    },
    "aud": "003_012_004",
    "img": "/img/book.png"
  },
  {
    "id": 15,
    "text": {
      "ar": "وَتُحْشَرُونَ",
      "en": "and you will be gathered",
      "tr": "watuḥ'sharūna",
      "ru": "и собраны"
    },
    "aud": "003_012_005",
    "img": "/img/book.png"
  },
  {
    "id": 16,
    "text": {
      "ar": "الْتَقَتَا",
      "en": "which met",
      "tr": "l-taqatā",
      "ru": "(которые) встретились они двое:"
    },
    "aud": "003_013_007",
    "img": "/img/book.png"
  },
  {
    "id": 17,
    "text": {
      "ar": "تُقَاتِلُ",
      "en": "fighting",
      "tr": "tuqātilu",
      "ru": "сражается"
    },
    "aud": "003_013_009",
    "img": "/img/book.png"
  },
  {
    "id": 18,
    "text": {
      "ar": "كَافِرَةٌ",
      "en": "disbelievers",
      "tr": "kāfiratun",
      "ru": "неверующее."
    },
    "aud": "003_013_014",
    "img": "/img/book.png"
  },
  {
    "id": 19,
    "text": {
      "ar": "يَرَوْنَهُمْ",
      "en": "They were seeing them",
      "tr": "yarawnahum",
      "ru": "Видели они их"
    },
    "aud": "003_013_015",
    "img": "/img/book.png"
  },
  {
    "id": 20,
    "text": {
      "ar": "مِثْلَيْهِمْ",
      "en": "twice of them",
      "tr": "mith'layhim",
      "ru": "вдвойне большими, чем они"
    },
    "aud": "003_013_016",
    "img": "/img/book.png"
  },
  {
    "id": 21,
    "text": {
      "ar": "رَأْيَ",
      "en": "with the sight",
      "tr": "raya",
      "ru": "на видение"
    },
    "aud": "003_013_017",
    "img": "/img/book.png"
  },
  {
    "id": 22,
    "text": {
      "ar": "الْعَيْنِ",
      "en": "(of) their eyes",
      "tr": "l-ʿayni",
      "ru": "глаза."
    },
    "aud": "003_013_018",
    "img": "/img/book.png"
  },
  {
    "id": 23,
    "text": {
      "ar": "يُؤَيِّدُ",
      "en": "supports",
      "tr": "yu-ayyidu",
      "ru": "подкрепляет"
    },
    "aud": "003_013_020",
    "img": "/img/book.png"
  },
  {
    "id": 24,
    "text": {
      "ar": "حُبُّ",
      "en": "(is) love",
      "tr": "ḥubbu",
      "ru": "любовь"
    },
    "aud": "003_014_003",
    "img": "/img/book.png"
  },
  {
    "id": 25,
    "text": {
      "ar": "وَالْبَنِينَ",
      "en": "and [the] sons",
      "tr": "wal-banīna",
      "ru": "и детей,"
    },
    "aud": "003_014_007",
    "img": "/img/book.png"
  },
  {
    "id": 26,
    "text": {
      "ar": "وَالْقَنَاطِيرِ",
      "en": "and [the] heaps",
      "tr": "wal-qanāṭīri",
      "ru": "и кинтаров [груд]"
    },
    "aud": "003_014_008",
    "img": "/img/book.png"
  },
  {
    "id": 27,
    "text": {
      "ar": "الْمُقَنْطَرَةِ",
      "en": "[the] stored up",
      "tr": "l-muqanṭarati",
      "ru": "нагроможденных"
    },
    "aud": "003_014_009",
    "img": "/img/book.png"
  },
  {
    "id": 28,
    "text": {
      "ar": "الذَّهَبِ",
      "en": "[the] gold",
      "tr": "l-dhahabi",
      "ru": "золота,"
    },
    "aud": "003_014_011",
    "img": "/img/book.png"
  },
  {
    "id": 29,
    "text": {
      "ar": "وَالْفِضَّةِ",
      "en": "and [the] silver",
      "tr": "wal-fiḍati",
      "ru": "и серебра,"
    },
    "aud": "003_014_012",
    "img": "/img/book.png"
  },
  {
    "id": 30,
    "text": {
      "ar": "وَالْخَيْلِ",
      "en": "and [the] horses",
      "tr": "wal-khayli",
      "ru": "и коней"
    },
    "aud": "003_014_013",
    "img": "/img/book.png"
  },
  {
    "id": 31,
    "text": {
      "ar": "الْمُسَوَّمَةِ",
      "en": "[the] branded",
      "tr": "l-musawamati",
      "ru": "меченных,"
    },
    "aud": "003_014_014",
    "img": "/img/book.png"
  },
  {
    "id": 32,
    "text": {
      "ar": "وَالْحَرْثِ",
      "en": "and [the] tilled land",
      "tr": "wal-ḥarthi",
      "ru": "и посевов."
    },
    "aud": "003_014_016",
    "img": "/img/book.png"
  },
  {
    "id": 33,
    "text": {
      "ar": "حُسْنُ",
      "en": "(is an) excellent",
      "tr": "ḥus'nu",
      "ru": "хорошее"
    },
    "aud": "003_014_023",
    "img": "/img/book.png"
  },
  {
    "id": 34,
    "text": {
      "ar": "الْمَءَابِ",
      "en": "[the] abode to return",
      "tr": "l-maābi",
      "ru": "пристанище!"
    },
    "aud": "003_014_024",
    "img": "/img/book.png"
  },
  {
    "id": 35,
    "text": {
      "ar": "أَؤُنَبِّئُكُمْ",
      "en": "Shall I inform you",
      "tr": "a-unabbi-ukum",
      "ru": "«(Не) сообщить ли вам"
    },
    "aud": "003_015_002",
    "img": "/img/book.png"
  },
  {
    "id": 36,
    "text": {
      "ar": "وَأَزْوَاجٌ",
      "en": "and spouses",
      "tr": "wa-azwājun",
      "ru": "и супруги"
    },
    "aud": "003_015_017",
    "img": "/img/book.png"
  },
  {
    "id": 37,
    "text": {
      "ar": "وَقِنَا",
      "en": "and save us",
      "tr": "waqinā",
      "ru": "и защити нас"
    },
    "aud": "003_016_009",
    "img": "/img/book.png"
  },
  {
    "id": 38,
    "text": {
      "ar": "وَالْمُنْفِقِينَ",
      "en": "and those who spend",
      "tr": "wal-munfiqīna",
      "ru": "и расходующих"
    },
    "aud": "003_017_004",
    "img": "/img/book.png"
  },
  {
    "id": 39,
    "text": {
      "ar": "وَالْمُسْتَغْفِرِينَ",
      "en": "and those who seek forgiveness",
      "tr": "wal-mus'taghfirīna",
      "ru": "и просящих прощение"
    },
    "aud": "003_017_005",
    "img": "/img/book.png"
  },
  {
    "id": 40,
    "text": {
      "ar": "بِالْأَسْحَارِ",
      "en": "[in the] before dawn",
      "tr": "bil-asḥāri",
      "ru": "в предрассветное время."
    },
    "aud": "003_017_006",
    "img": "/img/book.png"
  },
  {
    "id": 41,
    "text": {
      "ar": "الْإِسْلَامُ",
      "en": "(is) Islam",
      "tr": "l-is'lāmu",
      "ru": "Ислам."
    },
    "aud": "003_019_005",
    "img": "/img/book.png"
  },
  {
    "id": 42,
    "text": {
      "ar": "اخْتَلَفَ",
      "en": "differed",
      "tr": "ikh'talafa",
      "ru": "разошлись (во мнениях)"
    },
    "aud": "003_019_007",
    "img": "/img/book.png"
  },
  {
    "id": 43,
    "text": {
      "ar": "حَاجُّوكَ",
      "en": "they argue with you",
      "tr": "ḥājjūka",
      "ru": "станут они препираться с тобой,"
    },
    "aud": "003_020_002",
    "img": "/img/book.png"
  },
  {
    "id": 44,
    "text": {
      "ar": "أَسْلَمْتُ",
      "en": "I have submitted",
      "tr": "aslamtu",
      "ru": "«Предал я"
    },
    "aud": "003_020_004",
    "img": "/img/book.png"
  },
  {
    "id": 45,
    "text": {
      "ar": "اتَّبَعَنِ",
      "en": "follow me",
      "tr": "ittabaʿani",
      "ru": "последовали за мной."
    },
    "aud": "003_020_008",
    "img": "/img/book.png"
  },
  {
    "id": 46,
    "text": {
      "ar": "وَالْأُمِّيِّينَ",
      "en": "and the unlettered people",
      "tr": "wal-umiyīna",
      "ru": "и безграмотным:"
    },
    "aud": "003_020_013",
    "img": "/img/book.png"
  },
  {
    "id": 47,
    "text": {
      "ar": "ءَأَسْلَمْتُمْ",
      "en": "Have you submitted yourselves",
      "tr": "a-aslamtum",
      "ru": "«Предались ли вы?»"
    },
    "aud": "003_020_014",
    "img": "/img/book.png"
  },
  {
    "id": 48,
    "text": {
      "ar": "وَيَقْتُلُونَ",
      "en": "and they kill",
      "tr": "wayaqtulūna",
      "ru": "и убивают"
    },
    "aud": "003_021_006",
    "img": "/img/book.png"
  },
  {
    "id": 49,
    "text": {
      "ar": "تَمَسَّنَا",
      "en": "will touch us",
      "tr": "tamassanā",
      "ru": "коснётся нас"
    },
    "aud": "003_024_005",
    "img": "/img/book.png"
  },
  {
    "id": 50,
    "text": {
      "ar": "أَيَّامًا",
      "en": "(for) days",
      "tr": "ayyāman",
      "ru": "(на) дни"
    },
    "aud": "003_024_008",
    "img": "/img/book.png"
  },
  {
    "id": 51,
    "text": {
      "ar": "مَعْدُودَاتٍ",
      "en": "numbered",
      "tr": "maʿdūdātin",
      "ru": "исчисленные."
    },
    "aud": "003_024_009",
    "img": "/img/book.png"
  },
  {
    "id": 52,
    "text": {
      "ar": "وَغَرَّهُمْ",
      "en": "And deceived them",
      "tr": "wagharrahum",
      "ru": "И обольстило их"
    },
    "aud": "003_024_010",
    "img": "/img/book.png"
  },
  {
    "id": 53,
    "text": {
      "ar": "دِينِهِمْ",
      "en": "their religion",
      "tr": "dīnihim",
      "ru": "их верования"
    },
    "aud": "003_024_012",
    "img": "/img/book.png"
  },
  {
    "id": 54,
    "text": {
      "ar": "جَمَعْنَاهُمْ",
      "en": "We will gather them",
      "tr": "jamaʿnāhum",
      "ru": "соберём Мы их"
    },
    "aud": "003_025_003",
    "img": "/img/book.png"
  },
  {
    "id": 55,
    "text": {
      "ar": "مَالِكَ",
      "en": "Owner",
      "tr": "mālika",
      "ru": "Владыка"
    },
    "aud": "003_026_003",
    "img": "/img/book.png"
  },
  {
    "id": 56,
    "text": {
      "ar": "الْمُلْكَ",
      "en": "the dominion",
      "tr": "l-mul'ka",
      "ru": "власть,"
    },
    "aud": "003_026_006",
    "img": "/img/book.png"
  },
  {
    "id": 57,
    "text": {
      "ar": "وَتَنْزِعُ",
      "en": "and You take away",
      "tr": "watanziʿu",
      "ru": "и отнимаешь"
    },
    "aud": "003_026_009",
    "img": "/img/book.png"
  },
  {
    "id": 58,
    "text": {
      "ar": "وَتُعِزُّ",
      "en": "and You honor",
      "tr": "watuʿizzu",
      "ru": "И возвеличиваешь,"
    },
    "aud": "003_026_013",
    "img": "/img/book.png"
  },
  {
    "id": 59,
    "text": {
      "ar": "وَتُذِلُّ",
      "en": "and You humiliate",
      "tr": "watudhillu",
      "ru": "и унижаешь,"
    },
    "aud": "003_026_016",
    "img": "/img/book.png"
  },
  {
    "id": 60,
    "text": {
      "ar": "تُولِجُ",
      "en": "You cause to enter",
      "tr": "tūliju",
      "ru": "Вводишь Ты"
    },
    "aud": "003_027_001",
    "img": "/img/book.png"
  },
  {
    "id": 61,
    "text": {
      "ar": "وَتُولِجُ",
      "en": "and You cause to enter",
      "tr": "watūliju",
      "ru": "и вводишь"
    },
    "aud": "003_027_005",
    "img": "/img/book.png"
  },
  {
    "id": 62,
    "text": {
      "ar": "وَتُخْرِجُ",
      "en": "and You bring forth",
      "tr": "watukh'riju",
      "ru": "И выводишь Ты"
    },
    "aud": "003_027_009",
    "img": "/img/book.png"
  },
  {
    "id": 63,
    "text": {
      "ar": "وَتَرْزُقُ",
      "en": "and You give provision",
      "tr": "watarzuqu",
      "ru": "и наделяешь уделом,"
    },
    "aud": "003_027_017",
    "img": "/img/book.png"
  },
  {
    "id": 64,
    "text": {
      "ar": "تُقَاةً",
      "en": "(as) a precaution",
      "tr": "tuqātan",
      "ru": "остережением."
    },
    "aud": "003_028_021",
    "img": "/img/book.png"
  },
  {
    "id": 65,
    "text": {
      "ar": "وَيُحَذِّرُكُمُ",
      "en": "And warns you",
      "tr": "wayuḥadhirukumu",
      "ru": "И предостерегает вас"
    },
    "aud": "003_028_022",
    "img": "/img/book.png"
  },
  {
    "id": 66,
    "text": {
      "ar": "تُخْفُوا",
      "en": "you conceal",
      "tr": "tukh'fū",
      "ru": "вы скроете"
    },
    "aud": "003_029_003",
    "img": "/img/book.png"
  },
  {
    "id": 67,
    "text": {
      "ar": "تُبْدُوهُ",
      "en": "you disclose it",
      "tr": "tub'dūhu",
      "ru": "проявите это,"
    },
    "aud": "003_029_008",
    "img": "/img/book.png"
  },
  {
    "id": 68,
    "text": {
      "ar": "يَعْلَمْهُ",
      "en": "knows it",
      "tr": "yaʿlamhu",
      "ru": "знает его"
    },
    "aud": "003_029_009",
    "img": "/img/book.png"
  },
  {
    "id": 69,
    "text": {
      "ar": "مُحْضَرًا",
      "en": "presented",
      "tr": "muḥ'ḍaran",
      "ru": "представленным."
    },
    "aud": "003_030_009",
    "img": "/img/book.png"
  },
  {
    "id": 70,
    "text": {
      "ar": "تَوَدُّ",
      "en": "it will wish",
      "tr": "tawaddu",
      "ru": "будет желать она [душа],"
    },
    "aud": "003_030_014",
    "img": "/img/book.png"
  },
  {
    "id": 71,
    "text": {
      "ar": "يُحْبِبْكُمُ",
      "en": "will love you",
      "tr": "yuḥ'bib'kumu",
      "ru": "полюбит вас"
    },
    "aud": "003_031_007",
    "img": "/img/book.png"
  },
  {
    "id": 72,
    "text": {
      "ar": "وَءَالَ",
      "en": "and (the) family",
      "tr": "waāla",
      "ru": "и род"
    },
    "aud": "003_033_006",
    "img": "/img/book.png"
  },
  {
    "id": 73,
    "text": {
      "ar": "بَطْنِي",
      "en": "my womb",
      "tr": "baṭnī",
      "ru": "утробе моей,"
    },
    "aud": "003_035_011",
    "img": "/img/book.png"
  },
  {
    "id": 74,
    "text": {
      "ar": "مُحَرَّرًا",
      "en": "dedicated",
      "tr": "muḥarraran",
      "ru": "(будучи) освобожденным (для Тебя)."
    },
    "aud": "003_035_012",
    "img": "/img/book.png"
  },
  {
    "id": 75,
    "text": {
      "ar": "فَتَقَبَّلْ",
      "en": "so accept",
      "tr": "fataqabbal",
      "ru": "Прими же"
    },
    "aud": "003_035_013",
    "img": "/img/book.png"
  },
  {
    "id": 76,
    "text": {
      "ar": "وَضَعَتْهَا",
      "en": "she delivered her",
      "tr": "waḍaʿathā",
      "ru": "она сложила её,"
    },
    "aud": "003_036_002",
    "img": "/img/book.png"
  },
  {
    "id": 77,
    "text": {
      "ar": "وَضَعْتُهَا",
      "en": "[I] (have) delivered [her]",
      "tr": "waḍaʿtuhā",
      "ru": "сложила [родила] её"
    },
    "aud": "003_036_006",
    "img": "/img/book.png"
  },
  {
    "id": 78,
    "text": {
      "ar": "وَضَعَتْ",
      "en": "she delivered",
      "tr": "waḍaʿat",
      "ru": "она сложила."
    },
    "aud": "003_036_011",
    "img": "/img/book.png"
  },
  {
    "id": 79,
    "text": {
      "ar": "كَالْأُنْثَى",
      "en": "like the female",
      "tr": "kal-unthā",
      "ru": "подобным женскому полу."
    },
    "aud": "003_036_014",
    "img": "/img/book.png"
  },
  {
    "id": 80,
    "text": {
      "ar": "سَمَّيْتُهَا",
      "en": "[I] (have) named her",
      "tr": "sammaytuhā",
      "ru": "назвала её"
    },
    "aud": "003_036_016",
    "img": "/img/book.png"
  },
  {
    "id": 81,
    "text": {
      "ar": "أُعِيذُهَا",
      "en": "[I] seek refuge for her",
      "tr": "uʿīdhuhā",
      "ru": "обращаюсь за защитой её"
    },
    "aud": "003_036_019",
    "img": "/img/book.png"
  },
  {
    "id": 82,
    "text": {
      "ar": "وَذُرِّيَّتَهَا",
      "en": "and her offspring",
      "tr": "wadhurriyyatahā",
      "ru": "и её потомства"
    },
    "aud": "003_036_021",
    "img": "/img/book.png"
  },
  {
    "id": 83,
    "text": {
      "ar": "فَتَقَبَّلَهَا",
      "en": "So accepted her",
      "tr": "fataqabbalahā",
      "ru": "И принял её"
    },
    "aud": "003_037_001",
    "img": "/img/book.png"
  },
  {
    "id": 84,
    "text": {
      "ar": "رَبُّهَا",
      "en": "her Lord",
      "tr": "rabbuhā",
      "ru": "Господь её"
    },
    "aud": "003_037_002",
    "img": "/img/book.png"
  },
  {
    "id": 85,
    "text": {
      "ar": "بِقَبُولٍ",
      "en": "with acceptance",
      "tr": "biqabūlin",
      "ru": "с приёмом"
    },
    "aud": "003_037_003",
    "img": "/img/book.png"
  },
  {
    "id": 86,
    "text": {
      "ar": "حَسَنٍ",
      "en": "good",
      "tr": "ḥasanin",
      "ru": "хорошим"
    },
    "aud": "003_037_004",
    "img": "/img/book.png"
  },
  {
    "id": 87,
    "text": {
      "ar": "وَأَنْبَتَهَا",
      "en": "and made her grow",
      "tr": "wa-anbatahā",
      "ru": "и взрастил её"
    },
    "aud": "003_037_005",
    "img": "/img/book.png"
  },
  {
    "id": 88,
    "text": {
      "ar": "وَكَفَّلَهَا",
      "en": "and put her in (the) care",
      "tr": "wakaffalahā",
      "ru": "И поручил Он её"
    },
    "aud": "003_037_008",
    "img": "/img/book.png"
  },
  {
    "id": 89,
    "text": {
      "ar": "سَمِيعُ",
      "en": "(are) All-Hearer",
      "tr": "samīʿu",
      "ru": "слышащий"
    },
    "aud": "003_038_014",
    "img": "/img/book.png"
  },
  {
    "id": 90,
    "text": {
      "ar": "فَنَادَتْهُ",
      "en": "Then called him",
      "tr": "fanādathu",
      "ru": "И воззвали к нему"
    },
    "aud": "003_039_001",
    "img": "/img/book.png"
  },
  {
    "id": 91,
    "text": {
      "ar": "يُبَشِّرُكَ",
      "en": "gives you glad tidings",
      "tr": "yubashiruka",
      "ru": "радует тебя вестью"
    },
    "aud": "003_039_010",
    "img": "/img/book.png"
  },
  {
    "id": 92,
    "text": {
      "ar": "بِيَحْيَى",
      "en": "of Yahya",
      "tr": "biyaḥyā",
      "ru": "о Йахье,"
    },
    "aud": "003_039_011",
    "img": "/img/book.png"
  },
  {
    "id": 93,
    "text": {
      "ar": "بِكَلِمَةٍ",
      "en": "[of] a Word",
      "tr": "bikalimatin",
      "ru": "(некоего) слова"
    },
    "aud": "003_039_013",
    "img": "/img/book.png"
  },
  {
    "id": 94,
    "text": {
      "ar": "وَسَيِّدًا",
      "en": "and a noble",
      "tr": "wasayyidan",
      "ru": "и (о) господине,"
    },
    "aud": "003_039_016",
    "img": "/img/book.png"
  },
  {
    "id": 95,
    "text": {
      "ar": "وَحَصُورًا",
      "en": "and chaste",
      "tr": "waḥaṣūran",
      "ru": "и воздержанном"
    },
    "aud": "003_039_017",
    "img": "/img/book.png"
  },
  {
    "id": 96,
    "text": {
      "ar": "وَنَبِيًّا",
      "en": "and a Prophet",
      "tr": "wanabiyyan",
      "ru": "и (о) пророке"
    },
    "aud": "003_039_018",
    "img": "/img/book.png"
  },
  {
    "id": 97,
    "text": {
      "ar": "بَلَغَنِيَ",
      "en": "has reached me",
      "tr": "balaghaniya",
      "ru": "достигла меня"
    },
    "aud": "003_040_008",
    "img": "/img/book.png"
  },
  {
    "id": 98,
    "text": {
      "ar": "وَامْرَأَتِي",
      "en": "and my wife",
      "tr": "wa-im'ra-atī",
      "ru": "а жена моя –"
    },
    "aud": "003_040_010",
    "img": "/img/book.png"
  },
  {
    "id": 99,
    "text": {
      "ar": "عَاقِرٌ",
      "en": "(is) [a] barren",
      "tr": "ʿāqirun",
      "ru": "бесплодна?"
    },
    "aud": "003_040_011",
    "img": "/img/book.png"
  },
  {
    "id": 100,
    "text": {
      "ar": "رَمْزًا",
      "en": "(with) gestures",
      "tr": "ramzan",
      "ru": "знаками."
    },
    "aud": "003_041_014",
    "img": "/img/book.png"
  },
  {
    "id": 101,
    "text": {
      "ar": "اصْطَفَاكِ",
      "en": "(has) chosen you",
      "tr": "iṣ'ṭafāki",
      "ru": "избрал тебя"
    },
    "aud": "003_042_007",
    "img": "/img/book.png"
  },
  {
    "id": 102,
    "text": {
      "ar": "وَطَهَّرَكِ",
      "en": "and purified you",
      "tr": "waṭahharaki",
      "ru": "и очистил тебя."
    },
    "aud": "003_042_008",
    "img": "/img/book.png"
  },
  {
    "id": 103,
    "text": {
      "ar": "وَاصْطَفَاكِ",
      "en": "and chosen you",
      "tr": "wa-iṣ'ṭafāki",
      "ru": "И избрал тебя"
    },
    "aud": "003_042_009",
    "img": "/img/book.png"
  },
  {
    "id": 104,
    "text": {
      "ar": "نِسَاءِ",
      "en": "(the) women",
      "tr": "nisāi",
      "ru": "женщинами"
    },
    "aud": "003_042_011",
    "img": "/img/book.png"
  },
  {
    "id": 105,
    "text": {
      "ar": "اقْنُتِي",
      "en": "Be obedient",
      "tr": "uq'nutī",
      "ru": "всецело подчинись"
    },
    "aud": "003_043_002",
    "img": "/img/book.png"
  },
  {
    "id": 106,
    "text": {
      "ar": "لِرَبِّكِ",
      "en": "to your Lord",
      "tr": "lirabbiki",
      "ru": "Господу твоему,"
    },
    "aud": "003_043_003",
    "img": "/img/book.png"
  },
  {
    "id": 107,
    "text": {
      "ar": "وَاسْجُدِي",
      "en": "and prostrate",
      "tr": "wa-us'judī",
      "ru": "и преклоняйся ниц"
    },
    "aud": "003_043_004",
    "img": "/img/book.png"
  },
  {
    "id": 108,
    "text": {
      "ar": "وَارْكَعِي",
      "en": "and bow down",
      "tr": "wa-ir'kaʿī",
      "ru": "и кланяйся"
    },
    "aud": "003_043_005",
    "img": "/img/book.png"
  },
  {
    "id": 109,
    "text": {
      "ar": "الرَّاكِعِينَ",
      "en": "those who bow down",
      "tr": "l-rākiʿīna",
      "ru": "кланяющимися!»"
    },
    "aud": "003_043_007",
    "img": "/img/book.png"
  },
  {
    "id": 110,
    "text": {
      "ar": "أَقْلَامَهُمْ",
      "en": "their pens",
      "tr": "aqlāmahum",
      "ru": "свои письменные трости, (чтобы решить)"
    },
    "aud": "003_044_012",
    "img": "/img/book.png"
  },
  {
    "id": 111,
    "text": {
      "ar": "يَكْفُلُ",
      "en": "takes charge (of)",
      "tr": "yakfulu",
      "ru": "будет опекать"
    },
    "aud": "003_044_014",
    "img": "/img/book.png"
  },
  {
    "id": 112,
    "text": {
      "ar": "يُبَشِّرُكِ",
      "en": "gives you glad tidings",
      "tr": "yubashiruki",
      "ru": "радует тебя вестью"
    },
    "aud": "003_045_007",
    "img": "/img/book.png"
  },
  {
    "id": 113,
    "text": {
      "ar": "وَيُكَلِّمُ",
      "en": "And he will speak",
      "tr": "wayukallimu",
      "ru": "И будет говорить он"
    },
    "aud": "003_046_001",
    "img": "/img/book.png"
  },
  {
    "id": 114,
    "text": {
      "ar": "وَيُعَلِّمُهُ",
      "en": "And He will teach him",
      "tr": "wayuʿallimuhu",
      "ru": "И научит Он его"
    },
    "aud": "003_048_001",
    "img": "/img/book.png"
  },
  {
    "id": 115,
    "text": {
      "ar": "وَرَسُولًا",
      "en": "And (make him) a Messenger",
      "tr": "warasūlan",
      "ru": "и (сделает его) посланником"
    },
    "aud": "003_049_001",
    "img": "/img/book.png"
  },
  {
    "id": 116,
    "text": {
      "ar": "أَخْلُقُ",
      "en": "[I] design",
      "tr": "akhluqu",
      "ru": "сотворю я"
    },
    "aud": "003_049_012",
    "img": "/img/book.png"
  },
  {
    "id": 117,
    "text": {
      "ar": "فَأَنْفُخُ",
      "en": "then I breath",
      "tr": "fa-anfukhu",
      "ru": "и (затем) подую я"
    },
    "aud": "003_049_018",
    "img": "/img/book.png"
  },
  {
    "id": 118,
    "text": {
      "ar": "وَأُبْرِئُ",
      "en": "And I cure",
      "tr": "wa-ub'ri-u",
      "ru": "И исцеляю я"
    },
    "aud": "003_049_024",
    "img": "/img/book.png"
  },
  {
    "id": 119,
    "text": {
      "ar": "وَأُحْيِي",
      "en": "and I give life",
      "tr": "wa-uḥ'yī",
      "ru": "и оживляю я"
    },
    "aud": "003_049_027",
    "img": "/img/book.png"
  },
  {
    "id": 120,
    "text": {
      "ar": "وَأُنَبِّئُكُمْ",
      "en": "And I inform you",
      "tr": "wa-unabbi-ukum",
      "ru": "И сообщу я вам"
    },
    "aud": "003_049_031",
    "img": "/img/book.png"
  },
  {
    "id": 121,
    "text": {
      "ar": "تَدَّخِرُونَ",
      "en": "you store",
      "tr": "taddakhirūna",
      "ru": "запасаете вы"
    },
    "aud": "003_049_035",
    "img": "/img/book.png"
  },
  {
    "id": 122,
    "text": {
      "ar": "وَلِأُحِلَّ",
      "en": "and so that I make lawful",
      "tr": "wali-uḥilla",
      "ru": "и чтобы сделал я дозволенным"
    },
    "aud": "003_050_007",
    "img": "/img/book.png"
  },
  {
    "id": 123,
    "text": {
      "ar": "حُرِّمَ",
      "en": "was forbidden",
      "tr": "ḥurrima",
      "ru": "было сделано запретным"
    },
    "aud": "003_050_011",
    "img": "/img/book.png"
  },
  {
    "id": 124,
    "text": {
      "ar": "وَجِئْتُكُمْ",
      "en": "And I (have) come to you",
      "tr": "waji'tukum",
      "ru": "И пришёл я к вам"
    },
    "aud": "003_050_013",
    "img": "/img/book.png"
  },
  {
    "id": 125,
    "text": {
      "ar": "أَحَسَّ",
      "en": "perceived",
      "tr": "aḥassa",
      "ru": "почувствовал"
    },
    "aud": "003_052_002",
    "img": "/img/book.png"
  },
  {
    "id": 126,
    "text": {
      "ar": "بِأَنَّا",
      "en": "that we",
      "tr": "bi-annā",
      "ru": "что мы –"
    },
    "aud": "003_052_019",
    "img": "/img/book.png"
  },
  {
    "id": 127,
    "text": {
      "ar": "وَاتَّبَعْنَا",
      "en": "and we follow[ed]",
      "tr": "wa-ittabaʿnā",
      "ru": "и последовали мы"
    },
    "aud": "003_053_005",
    "img": "/img/book.png"
  },
  {
    "id": 128,
    "text": {
      "ar": "وَمَكَرَ",
      "en": "and planned",
      "tr": "wamakara",
      "ru": "и устроил хитрость"
    },
    "aud": "003_054_002",
    "img": "/img/book.png"
  },
  {
    "id": 129,
    "text": {
      "ar": "مُتَوَفِّيكَ",
      "en": "(will) take you",
      "tr": "mutawaffīka",
      "ru": "упокаивающим тебя,"
    },
    "aud": "003_055_006",
    "img": "/img/book.png"
  },
  {
    "id": 130,
    "text": {
      "ar": "وَرَافِعُكَ",
      "en": "and raise you",
      "tr": "warāfiʿuka",
      "ru": "и вознесящим тебя"
    },
    "aud": "003_055_007",
    "img": "/img/book.png"
  },
  {
    "id": 131,
    "text": {
      "ar": "وَمُطَهِّرُكَ",
      "en": "and purify you",
      "tr": "wamuṭahhiruka",
      "ru": "и (буду Я) очищающим тебя"
    },
    "aud": "003_055_009",
    "img": "/img/book.png"
  },
  {
    "id": 132,
    "text": {
      "ar": "وَجَاعِلُ",
      "en": "and I will make",
      "tr": "wajāʿilu",
      "ru": "и (буду Я) делающим"
    },
    "aud": "003_055_013",
    "img": "/img/book.png"
  },
  {
    "id": 133,
    "text": {
      "ar": "اتَّبَعُوكَ",
      "en": "follow[ed] you",
      "tr": "ittabaʿūka",
      "ru": "последовали за тобой,"
    },
    "aud": "003_055_015",
    "img": "/img/book.png"
  },
  {
    "id": 134,
    "text": {
      "ar": "فَأَحْكُمُ",
      "en": "and I will judge",
      "tr": "fa-aḥkumu",
      "ru": "и Я рассужу"
    },
    "aud": "003_055_025",
    "img": "/img/book.png"
  },
  {
    "id": 135,
    "text": {
      "ar": "فَأُعَذِّبُهُمْ",
      "en": "then I will punish them",
      "tr": "fa-uʿadhibuhum",
      "ru": "то Я накажу их"
    },
    "aud": "003_056_004",
    "img": "/img/book.png"
  },
  {
    "id": 136,
    "text": {
      "ar": "نَتْلُوهُ",
      "en": "(is what) We recite [it]",
      "tr": "natlūhu",
      "ru": "читаем Мы что"
    },
    "aud": "003_058_002",
    "img": "/img/book.png"
  },
  {
    "id": 137,
    "text": {
      "ar": "وَالذِّكْرِ",
      "en": "and the Reminder",
      "tr": "wal-dhik'ri",
      "ru": "и Напоминания"
    },
    "aud": "003_058_006",
    "img": "/img/book.png"
  },
  {
    "id": 138,
    "text": {
      "ar": "حَاجَّكَ",
      "en": "argues (with) you",
      "tr": "ḥājjaka",
      "ru": "(будет) препираться с тобой"
    },
    "aud": "003_061_002",
    "img": "/img/book.png"
  },
  {
    "id": 139,
    "text": {
      "ar": "نَدْعُ",
      "en": "let us call",
      "tr": "nadʿu",
      "ru": "позовём мы"
    },
    "aud": "003_061_012",
    "img": "/img/book.png"
  },
  {
    "id": 140,
    "text": {
      "ar": "أَبْنَاءَنَا",
      "en": "our sons",
      "tr": "abnāanā",
      "ru": "наших сынов"
    },
    "aud": "003_061_013",
    "img": "/img/book.png"
  },
  {
    "id": 141,
    "text": {
      "ar": "وَأَبْنَاءَكُمْ",
      "en": "and your sons",
      "tr": "wa-abnāakum",
      "ru": "и ваших сынов,"
    },
    "aud": "003_061_014",
    "img": "/img/book.png"
  },
  {
    "id": 142,
    "text": {
      "ar": "وَنِسَاءَنَا",
      "en": "and our women",
      "tr": "wanisāanā",
      "ru": "и наших женщин"
    },
    "aud": "003_061_015",
    "img": "/img/book.png"
  },
  {
    "id": 143,
    "text": {
      "ar": "وَنِسَاءَكُمْ",
      "en": "and your women",
      "tr": "wanisāakum",
      "ru": "и ваших женщин,"
    },
    "aud": "003_061_016",
    "img": "/img/book.png"
  },
  {
    "id": 144,
    "text": {
      "ar": "وَأَنْفُسَنَا",
      "en": "and ourselves",
      "tr": "wa-anfusanā",
      "ru": "и нас самих"
    },
    "aud": "003_061_017",
    "img": "/img/book.png"
  },
  {
    "id": 145,
    "text": {
      "ar": "وَأَنْفُسَكُمْ",
      "en": "and yourselves",
      "tr": "wa-anfusakum",
      "ru": "и вас самих,"
    },
    "aud": "003_061_018",
    "img": "/img/book.png"
  },
  {
    "id": 146,
    "text": {
      "ar": "نَبْتَهِلْ",
      "en": "let us pray humbly",
      "tr": "nabtahil",
      "ru": "обратимся мы о проклятии"
    },
    "aud": "003_061_020",
    "img": "/img/book.png"
  },
  {
    "id": 147,
    "text": {
      "ar": "فَنَجْعَلْ",
      "en": "and [we] invoke",
      "tr": "fanajʿal",
      "ru": "и (затем) призовём"
    },
    "aud": "003_061_021",
    "img": "/img/book.png"
  },
  {
    "id": 148,
    "text": {
      "ar": "لَعْنَتَ",
      "en": "(the) curse",
      "tr": "laʿnata",
      "ru": "проклятие"
    },
    "aud": "003_061_022",
    "img": "/img/book.png"
  },
  {
    "id": 149,
    "text": {
      "ar": "الْقَصَصُ",
      "en": "the narration",
      "tr": "l-qaṣaṣu",
      "ru": "рассказ"
    },
    "aud": "003_062_004",
    "img": "/img/book.png"
  },
  {
    "id": 150,
    "text": {
      "ar": "اشْهَدُوا",
      "en": "Bear witness",
      "tr": "ish'hadū",
      "ru": "«Засвидетельствуйте,"
    },
    "aud": "003_064_029",
    "img": "/img/book.png"
  },
  {
    "id": 151,
    "text": {
      "ar": "تُحَاجُّونَ",
      "en": "(do) you argue",
      "tr": "tuḥājjūna",
      "ru": "спорите вы"
    },
    "aud": "003_065_004",
    "img": "/img/book.png"
  },
  {
    "id": 152,
    "text": {
      "ar": "أُنْزِلَتِ",
      "en": "was revealed",
      "tr": "unzilati",
      "ru": "была ниспослана"
    },
    "aud": "003_065_008",
    "img": "/img/book.png"
  },
  {
    "id": 153,
    "text": {
      "ar": "وَالْإِنْجِيلُ",
      "en": "and the Injeel",
      "tr": "wal-injīlu",
      "ru": "и Евангелие,"
    },
    "aud": "003_065_010",
    "img": "/img/book.png"
  },
  {
    "id": 154,
    "text": {
      "ar": "حَاجَجْتُمْ",
      "en": "argued",
      "tr": "ḥājajtum",
      "ru": "спорили вы"
    },
    "aud": "003_066_003",
    "img": "/img/book.png"
  },
  {
    "id": 155,
    "text": {
      "ar": "يَهُودِيًّا",
      "en": "a Jew",
      "tr": "yahūdiyyan",
      "ru": "(ни) иудеем,"
    },
    "aud": "003_067_004",
    "img": "/img/book.png"
  },
  {
    "id": 156,
    "text": {
      "ar": "نَصْرَانِيًّا",
      "en": "a Christian",
      "tr": "naṣrāniyyan",
      "ru": "христианином,"
    },
    "aud": "003_067_006",
    "img": "/img/book.png"
  },
  {
    "id": 157,
    "text": {
      "ar": "بِإِبْرَاهِيمَ",
      "en": "with Ibrahim",
      "tr": "bi-ib'rāhīma",
      "ru": "к Ибрахиму –"
    },
    "aud": "003_068_004",
    "img": "/img/book.png"
  },
  {
    "id": 158,
    "text": {
      "ar": "لَلَّذِينَ",
      "en": "(are) those who",
      "tr": "lalladhīna",
      "ru": "однозначно, те, которые"
    },
    "aud": "003_068_005",
    "img": "/img/book.png"
  },
  {
    "id": 159,
    "text": {
      "ar": "وَدَّتْ",
      "en": "Wished",
      "tr": "waddat",
      "ru": "Хотела бы"
    },
    "aud": "003_069_001",
    "img": "/img/book.png"
  },
  {
    "id": 160,
    "text": {
      "ar": "يُضِلُّونَكُمْ",
      "en": "they could lead you astray",
      "tr": "yuḍillūnakum",
      "ru": "ввести вас в заблуждение,"
    },
    "aud": "003_069_007",
    "img": "/img/book.png"
  },
  {
    "id": 161,
    "text": {
      "ar": "تَشْهَدُونَ",
      "en": "bear witness",
      "tr": "tashhadūna",
      "ru": "свидетельствуете?"
    },
    "aud": "003_070_008",
    "img": "/img/book.png"
  },
  {
    "id": 162,
    "text": {
      "ar": "تَلْبِسُونَ",
      "en": "do you mix",
      "tr": "talbisūna",
      "ru": "облекаете вы"
    },
    "aud": "003_071_004",
    "img": "/img/book.png"
  },
  {
    "id": 163,
    "text": {
      "ar": "وَتَكْتُمُونَ",
      "en": "and conceal",
      "tr": "wataktumūna",
      "ru": "и скрываете вы"
    },
    "aud": "003_071_007",
    "img": "/img/book.png"
  },
  {
    "id": 164,
    "text": {
      "ar": "وَاكْفُرُوا",
      "en": "and reject",
      "tr": "wa-uk'furū",
      "ru": "и проявите неверие"
    },
    "aud": "003_072_014",
    "img": "/img/book.png"
  },
  {
    "id": 165,
    "text": {
      "ar": "ءَاخِرَهُ",
      "en": "at its end",
      "tr": "ākhirahu",
      "ru": "в конце его."
    },
    "aud": "003_072_015",
    "img": "/img/book.png"
  },
  {
    "id": 166,
    "text": {
      "ar": "تَبِعَ",
      "en": "follows",
      "tr": "tabiʿa",
      "ru": "последовал"
    },
    "aud": "003_073_005",
    "img": "/img/book.png"
  },
  {
    "id": 167,
    "text": {
      "ar": "يُحَاجُّوكُمْ",
      "en": "they may argue with you",
      "tr": "yuḥājjūkum",
      "ru": "станут они препираться с вами"
    },
    "aud": "003_073_019",
    "img": "/img/book.png"
  },
  {
    "id": 168,
    "text": {
      "ar": "يَخْتَصُّ",
      "en": "He chooses",
      "tr": "yakhtaṣṣu",
      "ru": "Избирает Он"
    },
    "aud": "003_074_001",
    "img": "/img/book.png"
  },
  {
    "id": 169,
    "text": {
      "ar": "بِرَحْمَتِهِ",
      "en": "for His Mercy",
      "tr": "biraḥmatihi",
      "ru": "Своим милосердием,"
    },
    "aud": "003_074_002",
    "img": "/img/book.png"
  },
  {
    "id": 170,
    "text": {
      "ar": "تَأْمَنْهُ",
      "en": "you entrust him",
      "tr": "tamanhu",
      "ru": "доверишь ты ему"
    },
    "aud": "003_075_006",
    "img": "/img/book.png"
  },
  {
    "id": 171,
    "text": {
      "ar": "بِقِنْطَارٍ",
      "en": "with a great amount of wealth",
      "tr": "biqinṭārin",
      "ru": "кинтар [большое имущество],"
    },
    "aud": "003_075_007",
    "img": "/img/book.png"
  },
  {
    "id": 172,
    "text": {
      "ar": "يُؤَدِّهِ",
      "en": "he will return it",
      "tr": "yu-addihi",
      "ru": "вернёт он его"
    },
    "aud": "003_075_008",
    "img": "/img/book.png"
  },
  {
    "id": 173,
    "text": {
      "ar": "بِدِينَارٍ",
      "en": "with a single coin",
      "tr": "bidīnārin",
      "ru": "динар,"
    },
    "aud": "003_075_014",
    "img": "/img/book.png"
  },
  {
    "id": 174,
    "text": {
      "ar": "دُمْتَ",
      "en": "you keep constantly",
      "tr": "dum'ta",
      "ru": "будешь продолжать ты быть"
    },
    "aud": "003_075_020",
    "img": "/img/book.png"
  },
  {
    "id": 175,
    "text": {
      "ar": "سَبِيلٌ",
      "en": "any [way] (accountability)",
      "tr": "sabīlun",
      "ru": "(никакого) пути,"
    },
    "aud": "003_075_030",
    "img": "/img/book.png"
  },
  {
    "id": 176,
    "text": {
      "ar": "وَأَيْمَانِهِمْ",
      "en": "and their oaths",
      "tr": "wa-aymānihim",
      "ru": "и свои клятвы"
    },
    "aud": "003_077_006",
    "img": "/img/book.png"
  },
  {
    "id": 177,
    "text": {
      "ar": "خَلَاقَ",
      "en": "share",
      "tr": "khalāqa",
      "ru": "(никакой) доли"
    },
    "aud": "003_077_011",
    "img": "/img/book.png"
  },
  {
    "id": 178,
    "text": {
      "ar": "يُكَلِّمُهُمُ",
      "en": "will speak to them",
      "tr": "yukallimuhumu",
      "ru": "будет говорить с ними"
    },
    "aud": "003_077_016",
    "img": "/img/book.png"
  },
  {
    "id": 179,
    "text": {
      "ar": "يُزَكِّيهِمْ",
      "en": "purify them",
      "tr": "yuzakkīhim",
      "ru": "очистит Он их."
    },
    "aud": "003_077_024",
    "img": "/img/book.png"
  },
  {
    "id": 180,
    "text": {
      "ar": "لَفَرِيقًا",
      "en": "surely (is) a group",
      "tr": "lafarīqan",
      "ru": "непременно (есть такая) часть,"
    },
    "aud": "003_078_003",
    "img": "/img/book.png"
  },
  {
    "id": 181,
    "text": {
      "ar": "يَلْوُونَ",
      "en": "they distort",
      "tr": "yalwūna",
      "ru": "(которые) искажают"
    },
    "aud": "003_078_004",
    "img": "/img/book.png"
  },
  {
    "id": 182,
    "text": {
      "ar": "أَلْسِنَتَهُمْ",
      "en": "their tongues",
      "tr": "alsinatahum",
      "ru": "свои языки"
    },
    "aud": "003_078_005",
    "img": "/img/book.png"
  },
  {
    "id": 183,
    "text": {
      "ar": "لِتَحْسَبُوهُ",
      "en": "so that you may think it",
      "tr": "litaḥsabūhu",
      "ru": "чтобы вы сочли это"
    },
    "aud": "003_078_007",
    "img": "/img/book.png"
  },
  {
    "id": 184,
    "text": {
      "ar": "يُؤْتِيَهُ",
      "en": "gives him",
      "tr": "yu'tiyahu",
      "ru": "дарует ему"
    },
    "aud": "003_079_005",
    "img": "/img/book.png"
  },
  {
    "id": 185,
    "text": {
      "ar": "رَبَّانِيِّينَ",
      "en": "worshippers of the Lord",
      "tr": "rabbāniyyīna",
      "ru": "воспитывающими (и обучающими) (людей),"
    },
    "aud": "003_079_021",
    "img": "/img/book.png"
  },
  {
    "id": 186,
    "text": {
      "ar": "تُعَلِّمُونَ",
      "en": "teaching",
      "tr": "tuʿallimūna",
      "ru": "обучаете"
    },
    "aud": "003_079_024",
    "img": "/img/book.png"
  },
  {
    "id": 187,
    "text": {
      "ar": "يَأْمُرَكُمْ",
      "en": "he will order you",
      "tr": "yamurakum",
      "ru": "(чтобы) повелевал он вам,"
    },
    "aud": "003_080_002",
    "img": "/img/book.png"
  },
  {
    "id": 188,
    "text": {
      "ar": "أَيَأْمُرُكُمْ",
      "en": "Would he order you",
      "tr": "ayamurukum",
      "ru": "Разве прикажет он вам"
    },
    "aud": "003_080_008",
    "img": "/img/book.png"
  },
  {
    "id": 189,
    "text": {
      "ar": "ءَاتَيْتُكُمْ",
      "en": "I (have) given you",
      "tr": "ātaytukum",
      "ru": "даровал Я вам"
    },
    "aud": "003_081_007",
    "img": "/img/book.png"
  },
  {
    "id": 190,
    "text": {
      "ar": "وَحِكْمَةٍ",
      "en": "and wisdom",
      "tr": "waḥik'matin",
      "ru": "и (какой бы ни было) мудрости,"
    },
    "aud": "003_081_010",
    "img": "/img/book.png"
  },
  {
    "id": 191,
    "text": {
      "ar": "لَتُؤْمِنُنَّ",
      "en": "you must believe",
      "tr": "latu'minunna",
      "ru": "(то) вы, однозначно и непременно, уверуете"
    },
    "aud": "003_081_017",
    "img": "/img/book.png"
  },
  {
    "id": 192,
    "text": {
      "ar": "وَلَتَنْصُرُنَّهُ",
      "en": "and you must help him",
      "tr": "walatanṣurunnahu",
      "ru": "и вы, однозначно и непременно, будете помогать ему»."
    },
    "aud": "003_081_019",
    "img": "/img/book.png"
  },
  {
    "id": 193,
    "text": {
      "ar": "ءَأَقْرَرْتُمْ",
      "en": "Do you affirm",
      "tr": "a-aqrartum",
      "ru": "«Подтверждаете ли вы"
    },
    "aud": "003_081_021",
    "img": "/img/book.png"
  },
  {
    "id": 194,
    "text": {
      "ar": "وَأَخَذْتُمْ",
      "en": "and take",
      "tr": "wa-akhadhtum",
      "ru": "и принимаете ли вы"
    },
    "aud": "003_081_022",
    "img": "/img/book.png"
  },
  {
    "id": 195,
    "text": {
      "ar": "إِصْرِي",
      "en": "My Covenant",
      "tr": "iṣ'rī",
      "ru": "Мою ношу?»"
    },
    "aud": "003_081_025",
    "img": "/img/book.png"
  },
  {
    "id": 196,
    "text": {
      "ar": "أَقْرَرْنَا",
      "en": "We affirm",
      "tr": "aqrarnā",
      "ru": "«Подтверждаем мы!»"
    },
    "aud": "003_081_027",
    "img": "/img/book.png"
  },
  {
    "id": 197,
    "text": {
      "ar": "فَاشْهَدُوا",
      "en": "Then bear witness",
      "tr": "fa-ish'hadū",
      "ru": "«Так будьте же свидетелями,"
    },
    "aud": "003_081_029",
    "img": "/img/book.png"
  },
  {
    "id": 198,
    "text": {
      "ar": "وَالنَّبِيُّونَ",
      "en": "and the Prophets",
      "tr": "wal-nabiyūna",
      "ru": "и пророкам"
    },
    "aud": "003_084_019",
    "img": "/img/book.png"
  },
  {
    "id": 199,
    "text": {
      "ar": "نُفَرِّقُ",
      "en": "we make distinction",
      "tr": "nufarriqu",
      "ru": "делаем мы различий"
    },
    "aud": "003_084_023",
    "img": "/img/book.png"
  },
  {
    "id": 200,
    "text": {
      "ar": "يَبْتَغِ",
      "en": "seeks",
      "tr": "yabtaghi",
      "ru": "желает"
    },
    "aud": "003_085_002",
    "img": "/img/book.png"
  },
  {
    "id": 201,
    "text": {
      "ar": "يُقْبَلَ",
      "en": "will be accepted",
      "tr": "yuq'bala",
      "ru": "будет принято оно"
    },
    "aud": "003_085_007",
    "img": "/img/book.png"
  },
  {
    "id": 202,
    "text": {
      "ar": "تَوْبَتُهُمْ",
      "en": "their repentance",
      "tr": "tawbatuhum",
      "ru": "их покаяние,"
    },
    "aud": "003_090_011",
    "img": "/img/book.png"
  },
  {
    "id": 203,
    "text": {
      "ar": "مِلْءُ",
      "en": "full",
      "tr": "mil'u",
      "ru": "(даже) полная"
    },
    "aud": "003_091_011",
    "img": "/img/book.png"
  },
  {
    "id": 204,
    "text": {
      "ar": "ذَهَبًا",
      "en": "(of) gold",
      "tr": "dhahaban",
      "ru": "золотом,"
    },
    "aud": "003_091_013",
    "img": "/img/book.png"
  },
  {
    "id": 205,
    "text": {
      "ar": "افْتَدَى",
      "en": "he offered as ransom",
      "tr": "if'tadā",
      "ru": "он (захотел) выкупить себя"
    },
    "aud": "003_091_015",
    "img": "/img/book.png"
  },
  {
    "id": 206,
    "text": {
      "ar": "تَنَالُوا",
      "en": "will you attain",
      "tr": "tanālū",
      "ru": "достигните вы"
    },
    "aud": "003_092_002",
    "img": "/img/book.png"
  },
  {
    "id": 207,
    "text": {
      "ar": "الْبِرَّ",
      "en": "[the] righteousness",
      "tr": "l-bira",
      "ru": "благочестия,"
    },
    "aud": "003_092_003",
    "img": "/img/book.png"
  },
  {
    "id": 208,
    "text": {
      "ar": "الطَّعَامِ",
      "en": "[the] food",
      "tr": "l-ṭaʿāmi",
      "ru": "пища"
    },
    "aud": "003_093_002",
    "img": "/img/book.png"
  },
  {
    "id": 209,
    "text": {
      "ar": "حِلًّا",
      "en": "lawful",
      "tr": "ḥillan",
      "ru": "дозволена"
    },
    "aud": "003_093_004",
    "img": "/img/book.png"
  },
  {
    "id": 210,
    "text": {
      "ar": "إِسْرَاءِيلُ",
      "en": "Israel",
      "tr": "is'rāīlu",
      "ru": "Исраил"
    },
    "aud": "003_093_010",
    "img": "/img/book.png"
  },
  {
    "id": 211,
    "text": {
      "ar": "بِالتَّوْرَاةِ",
      "en": "the Taurat",
      "tr": "bil-tawrāti",
      "ru": "Тору"
    },
    "aud": "003_093_020",
    "img": "/img/book.png"
  },
  {
    "id": 212,
    "text": {
      "ar": "فَاتْلُوهَا",
      "en": "and recite it",
      "tr": "fa-it'lūhā",
      "ru": "и читайте же её,"
    },
    "aud": "003_093_021",
    "img": "/img/book.png"
  },
  {
    "id": 213,
    "text": {
      "ar": "فَاتَّبِعُوا",
      "en": "then follow",
      "tr": "fa-ittabiʿū",
      "ru": "так следуйте же"
    },
    "aud": "003_095_004",
    "img": "/img/book.png"
  },
  {
    "id": 214,
    "text": {
      "ar": "وُضِعَ",
      "en": "set up",
      "tr": "wuḍiʿa",
      "ru": "(который) был установлен"
    },
    "aud": "003_096_004",
    "img": "/img/book.png"
  },
  {
    "id": 215,
    "text": {
      "ar": "لَلَّذِي",
      "en": "(is) the one which",
      "tr": "lalladhī",
      "ru": "однозначно, тот, который"
    },
    "aud": "003_096_006",
    "img": "/img/book.png"
  },
  {
    "id": 216,
    "text": {
      "ar": "بِبَكَّةَ",
      "en": "(is) at Bakkah",
      "tr": "bibakkata",
      "ru": "в Бекке [Мекке]"
    },
    "aud": "003_096_007",
    "img": "/img/book.png"
  },
  {
    "id": 217,
    "text": {
      "ar": "مَقَامُ",
      "en": "standing place",
      "tr": "maqāmu",
      "ru": "место"
    },
    "aud": "003_097_004",
    "img": "/img/book.png"
  },
  {
    "id": 218,
    "text": {
      "ar": "دَخَلَهُ",
      "en": "enters it",
      "tr": "dakhalahu",
      "ru": "войдёт в него,"
    },
    "aud": "003_097_007",
    "img": "/img/book.png"
  },
  {
    "id": 219,
    "text": {
      "ar": "حِجُّ",
      "en": "(is) pilgrimage",
      "tr": "ḥijju",
      "ru": "совершение паломничество"
    },
    "aud": "003_097_013",
    "img": "/img/book.png"
  },
  {
    "id": 220,
    "text": {
      "ar": "اسْتَطَاعَ",
      "en": "is able",
      "tr": "is'taṭāʿa",
      "ru": "может [в состоянии совершить]"
    },
    "aud": "003_097_016",
    "img": "/img/book.png"
  },
  {
    "id": 221,
    "text": {
      "ar": "تَصُدُّونَ",
      "en": "(do) you hinder",
      "tr": "taṣuddūna",
      "ru": "вы отклоняете"
    },
    "aud": "003_099_005",
    "img": "/img/book.png"
  },
  {
    "id": 222,
    "text": {
      "ar": "تَبْغُونَهَا",
      "en": "seeking (to make) it",
      "tr": "tabghūnahā",
      "ru": "(при этом) желаете вы её [пути]"
    },
    "aud": "003_099_011",
    "img": "/img/book.png"
  },
  {
    "id": 223,
    "text": {
      "ar": "يَرُدُّوكُمْ",
      "en": "they will turn you back",
      "tr": "yaruddūkum",
      "ru": "обратят они вас"
    },
    "aud": "003_100_011",
    "img": "/img/book.png"
  },
  {
    "id": 224,
    "text": {
      "ar": "رَسُولُهُ",
      "en": "(is) His Messenger",
      "tr": "rasūluhu",
      "ru": "Его посланник?"
    },
    "aud": "003_101_009",
    "img": "/img/book.png"
  },
  {
    "id": 225,
    "text": {
      "ar": "يَعْتَصِمْ",
      "en": "holds firmly",
      "tr": "yaʿtaṣim",
      "ru": "(будет) держаться"
    },
    "aud": "003_101_011",
    "img": "/img/book.png"
  },
  {
    "id": 226,
    "text": {
      "ar": "هُدِيَ",
      "en": "he is guided",
      "tr": "hudiya",
      "ru": "направлен он"
    },
    "aud": "003_101_014",
    "img": "/img/book.png"
  },
  {
    "id": 227,
    "text": {
      "ar": "تُقَاتِهِ",
      "en": "(that) He (should) be feared",
      "tr": "tuqātihi",
      "ru": "остережением Его"
    },
    "aud": "003_102_007",
    "img": "/img/book.png"
  },
  {
    "id": 228,
    "text": {
      "ar": "تَمُوتُنَّ",
      "en": "die",
      "tr": "tamūtunna",
      "ru": "умирайте (никак),"
    },
    "aud": "003_102_009",
    "img": "/img/book.png"
  },
  {
    "id": 229,
    "text": {
      "ar": "بِحَبْلِ",
      "en": "to (the) rope",
      "tr": "biḥabli",
      "ru": "за вервь"
    },
    "aud": "003_103_002",
    "img": "/img/book.png"
  },
  {
    "id": 230,
    "text": {
      "ar": "فَأَلَّفَ",
      "en": "then He made friendship",
      "tr": "fa-allafa",
      "ru": "но (затем) привёл Он к согласию"
    },
    "aud": "003_103_014",
    "img": "/img/book.png"
  },
  {
    "id": 231,
    "text": {
      "ar": "بِنِعْمَتِهِ",
      "en": "by His Favor",
      "tr": "biniʿ'matihi",
      "ru": "по Его благодеянию"
    },
    "aud": "003_103_018",
    "img": "/img/book.png"
  },
  {
    "id": 232,
    "text": {
      "ar": "حُفْرَةٍ",
      "en": "(of) pit",
      "tr": "ḥuf'ratin",
      "ru": "пропасти"
    },
    "aud": "003_103_023",
    "img": "/img/book.png"
  },
  {
    "id": 233,
    "text": {
      "ar": "فَأَنْقَذَكُمْ",
      "en": "then He saved you",
      "tr": "fa-anqadhakum",
      "ru": "и (затем) спас Он вас"
    },
    "aud": "003_103_026",
    "img": "/img/book.png"
  },
  {
    "id": 234,
    "text": {
      "ar": "وَلْتَكُنْ",
      "en": "And let there be",
      "tr": "waltakun",
      "ru": "И пусть будет"
    },
    "aud": "003_104_001",
    "img": "/img/book.png"
  },
  {
    "id": 235,
    "text": {
      "ar": "وَاخْتَلَفُوا",
      "en": "and differed",
      "tr": "wa-ikh'talafū",
      "ru": "и впали в разногласия"
    },
    "aud": "003_105_005",
    "img": "/img/book.png"
  },
  {
    "id": 236,
    "text": {
      "ar": "تَبْيَضُّ",
      "en": "would become white",
      "tr": "tabyaḍḍu",
      "ru": "побелеют"
    },
    "aud": "003_106_002",
    "img": "/img/book.png"
  },
  {
    "id": 237,
    "text": {
      "ar": "وَتَسْوَدُّ",
      "en": "and would become black",
      "tr": "wataswaddu",
      "ru": "и почернеют"
    },
    "aud": "003_106_004",
    "img": "/img/book.png"
  },
  {
    "id": 238,
    "text": {
      "ar": "اسْوَدَّتْ",
      "en": "turn black",
      "tr": "is'waddat",
      "ru": "почернели"
    },
    "aud": "003_106_008",
    "img": "/img/book.png"
  },
  {
    "id": 239,
    "text": {
      "ar": "أَكَفَرْتُمْ",
      "en": "Did you disbelieve",
      "tr": "akafartum",
      "ru": "«Неужели вы стали неверующими"
    },
    "aud": "003_106_010",
    "img": "/img/book.png"
  },
  {
    "id": 240,
    "text": {
      "ar": "ابْيَضَّتْ",
      "en": "turn white",
      "tr": "ib'yaḍḍat",
      "ru": "побелели"
    },
    "aud": "003_107_003",
    "img": "/img/book.png"
  },
  {
    "id": 241,
    "text": {
      "ar": "أُخْرِجَتْ",
      "en": "raised",
      "tr": "ukh'rijat",
      "ru": "(которая) выведена"
    },
    "aud": "003_110_004",
    "img": "/img/book.png"
  },
  {
    "id": 242,
    "text": {
      "ar": "وَتَنْهَوْنَ",
      "en": "and forbidding",
      "tr": "watanhawna",
      "ru": "и удерживаете"
    },
    "aud": "003_110_008",
    "img": "/img/book.png"
  },
  {
    "id": 243,
    "text": {
      "ar": "وَتُؤْمِنُونَ",
      "en": "and believing",
      "tr": "watu'minūna",
      "ru": "и веруете вы"
    },
    "aud": "003_110_011",
    "img": "/img/book.png"
  },
  {
    "id": 244,
    "text": {
      "ar": "يَضُرُّوكُمْ",
      "en": "will they harm you",
      "tr": "yaḍurrūkum",
      "ru": "причинят вреда они вам"
    },
    "aud": "003_111_002",
    "img": "/img/book.png"
  },
  {
    "id": 245,
    "text": {
      "ar": "يُوَلُّوكُمُ",
      "en": "they will turn (towards) you",
      "tr": "yuwallūkumu",
      "ru": "(то) повернут к вам"
    },
    "aud": "003_111_007",
    "img": "/img/book.png"
  },
  {
    "id": 246,
    "text": {
      "ar": "ضُرِبَتْ",
      "en": "Struck",
      "tr": "ḍuribat",
      "ru": "Обрушено"
    },
    "aud": "003_112_001",
    "img": "/img/book.png"
  },
  {
    "id": 247,
    "text": {
      "ar": "الذِّلَّةُ",
      "en": "the humiliation",
      "tr": "l-dhilatu",
      "ru": "унижение,"
    },
    "aud": "003_112_003",
    "img": "/img/book.png"
  },
  {
    "id": 248,
    "text": {
      "ar": "بِحَبْلٍ",
      "en": "with a rope",
      "tr": "biḥablin",
      "ru": "с вервью"
    },
    "aud": "003_112_008",
    "img": "/img/book.png"
  },
  {
    "id": 249,
    "text": {
      "ar": "وَحَبْلٍ",
      "en": "and a rope",
      "tr": "waḥablin",
      "ru": "и вервью"
    },
    "aud": "003_112_011",
    "img": "/img/book.png"
  },
  {
    "id": 250,
    "text": {
      "ar": "وَبَاءُو",
      "en": "And they incurred",
      "tr": "wabāū",
      "ru": "И вернулись они"
    },
    "aud": "003_112_014",
    "img": "/img/book.png"
  },
  {
    "id": 251,
    "text": {
      "ar": "وَضُرِبَتْ",
      "en": "and struck",
      "tr": "waḍuribat",
      "ru": "и обрушена"
    },
    "aud": "003_112_018",
    "img": "/img/book.png"
  },
  {
    "id": 252,
    "text": {
      "ar": "الْمَسْكَنَةُ",
      "en": "the poverty",
      "tr": "l-maskanatu",
      "ru": "бедность."
    },
    "aud": "003_112_020",
    "img": "/img/book.png"
  },
  {
    "id": 253,
    "text": {
      "ar": "وَيُسَارِعُونَ",
      "en": "and they hasten",
      "tr": "wayusāriʿūna",
      "ru": "и спешат (друг перед другом)"
    },
    "aud": "003_114_010",
    "img": "/img/book.png"
  },
  {
    "id": 254,
    "text": {
      "ar": "يَفْعَلُوا",
      "en": "they do",
      "tr": "yafʿalū",
      "ru": "делали они"
    },
    "aud": "003_115_002",
    "img": "/img/book.png"
  },
  {
    "id": 255,
    "text": {
      "ar": "يُكْفَرُوهُ",
      "en": "will they be denied it",
      "tr": "yuk'farūhu",
      "ru": "отвергнуты они от него."
    },
    "aud": "003_115_006",
    "img": "/img/book.png"
  },
  {
    "id": 256,
    "text": {
      "ar": "رِيحٍ",
      "en": "(of) a wind",
      "tr": "rīḥin",
      "ru": "(некоего) ветра,"
    },
    "aud": "003_117_009",
    "img": "/img/book.png"
  },
  {
    "id": 257,
    "text": {
      "ar": "صِرٌّ",
      "en": "(is) frost",
      "tr": "ṣirrun",
      "ru": "мороз,"
    },
    "aud": "003_117_011",
    "img": "/img/book.png"
  },
  {
    "id": 258,
    "text": {
      "ar": "أَصَابَتْ",
      "en": "it struck",
      "tr": "aṣābat",
      "ru": "(который) поразил (ж.р.)"
    },
    "aud": "003_117_012",
    "img": "/img/book.png"
  },
  {
    "id": 259,
    "text": {
      "ar": "فَأَهْلَكَتْهُ",
      "en": "then destroyed it",
      "tr": "fa-ahlakathu",
      "ru": "и (затем) погубила его."
    },
    "aud": "003_117_017",
    "img": "/img/book.png"
  },
  {
    "id": 260,
    "text": {
      "ar": "بِطَانَةً",
      "en": "(as) intimates",
      "tr": "biṭānatan",
      "ru": "близкое окружение"
    },
    "aud": "003_118_006",
    "img": "/img/book.png"
  },
  {
    "id": 261,
    "text": {
      "ar": "دُونِكُمْ",
      "en": "other than yourselves",
      "tr": "dūnikum",
      "ru": "тех, кто помимо вас самих."
    },
    "aud": "003_118_008",
    "img": "/img/book.png"
  },
  {
    "id": 262,
    "text": {
      "ar": "يَأْلُونَكُمْ",
      "en": "they will spare you",
      "tr": "yalūnakum",
      "ru": "упустят они нанести вам"
    },
    "aud": "003_118_010",
    "img": "/img/book.png"
  },
  {
    "id": 263,
    "text": {
      "ar": "بَدَتِ",
      "en": "(has become) apparent",
      "tr": "badati",
      "ru": "проявилась"
    },
    "aud": "003_118_016",
    "img": "/img/book.png"
  },
  {
    "id": 264,
    "text": {
      "ar": "الْبَغْضَاءُ",
      "en": "the hatred",
      "tr": "l-baghḍāu",
      "ru": "ненависть"
    },
    "aud": "003_118_017",
    "img": "/img/book.png"
  },
  {
    "id": 265,
    "text": {
      "ar": "تُحِبُّونَهُمْ",
      "en": "you love them",
      "tr": "tuḥibbūnahum",
      "ru": "любите вы их,"
    },
    "aud": "003_119_003",
    "img": "/img/book.png"
  },
  {
    "id": 266,
    "text": {
      "ar": "يُحِبُّونَكُمْ",
      "en": "they love you",
      "tr": "yuḥibbūnakum",
      "ru": "любят они вас!"
    },
    "aud": "003_119_005",
    "img": "/img/book.png"
  },
  {
    "id": 267,
    "text": {
      "ar": "لَقُوكُمْ",
      "en": "they meet you",
      "tr": "laqūkum",
      "ru": "встречаются они с вами"
    },
    "aud": "003_119_010",
    "img": "/img/book.png"
  },
  {
    "id": 268,
    "text": {
      "ar": "عَضُّوا",
      "en": "they bite",
      "tr": "ʿaḍḍū",
      "ru": "кусают они"
    },
    "aud": "003_119_015",
    "img": "/img/book.png"
  },
  {
    "id": 269,
    "text": {
      "ar": "الْأَنَامِلَ",
      "en": "the finger tips",
      "tr": "l-anāmila",
      "ru": "кончики пальцев"
    },
    "aud": "003_119_017",
    "img": "/img/book.png"
  },
  {
    "id": 270,
    "text": {
      "ar": "مُوتُوا",
      "en": "Die",
      "tr": "mūtū",
      "ru": "«Умрите"
    },
    "aud": "003_119_021",
    "img": "/img/book.png"
  },
  {
    "id": 271,
    "text": {
      "ar": "بِغَيْظِكُمْ",
      "en": "in your rage",
      "tr": "bighayẓikum",
      "ru": "от своей злобы!"
    },
    "aud": "003_119_022",
    "img": "/img/book.png"
  },
  {
    "id": 272,
    "text": {
      "ar": "تَمْسَسْكُمْ",
      "en": "touches you",
      "tr": "tamsaskum",
      "ru": "коснётся вас"
    },
    "aud": "003_120_002",
    "img": "/img/book.png"
  },
  {
    "id": 273,
    "text": {
      "ar": "تُصِبْكُمْ",
      "en": "strikes you",
      "tr": "tuṣib'kum",
      "ru": "постигает вас"
    },
    "aud": "003_120_006",
    "img": "/img/book.png"
  },
  {
    "id": 274,
    "text": {
      "ar": "يَفْرَحُوا",
      "en": "they rejoice",
      "tr": "yafraḥū",
      "ru": "они радуются"
    },
    "aud": "003_120_008",
    "img": "/img/book.png"
  },
  {
    "id": 275,
    "text": {
      "ar": "غَدَوْتَ",
      "en": "you left early morning",
      "tr": "ghadawta",
      "ru": "вышел ты утром"
    },
    "aud": "003_121_002",
    "img": "/img/book.png"
  },
  {
    "id": 276,
    "text": {
      "ar": "تُبَوِّئُ",
      "en": "to post",
      "tr": "tubawwi-u",
      "ru": "расставляя ты"
    },
    "aud": "003_121_005",
    "img": "/img/book.png"
  },
  {
    "id": 277,
    "text": {
      "ar": "لِلْقِتَالِ",
      "en": "for the battle",
      "tr": "lil'qitāli",
      "ru": "для сражения."
    },
    "aud": "003_121_008",
    "img": "/img/book.png"
  },
  {
    "id": 278,
    "text": {
      "ar": "تَفْشَلَا",
      "en": "they lost heart",
      "tr": "tafshalā",
      "ru": "ослабеть (они двое) духом,"
    },
    "aud": "003_122_006",
    "img": "/img/book.png"
  },
  {
    "id": 279,
    "text": {
      "ar": "وَلِيُّهُمَا",
      "en": "(was) their protector",
      "tr": "waliyyuhumā",
      "ru": "Покровитель их двоих."
    },
    "aud": "003_122_008",
    "img": "/img/book.png"
  },
  {
    "id": 280,
    "text": {
      "ar": "بِبَدْرٍ",
      "en": "in Badr",
      "tr": "bibadrin",
      "ru": "при Бадре,"
    },
    "aud": "003_123_004",
    "img": "/img/book.png"
  },
  {
    "id": 281,
    "text": {
      "ar": "أَذِلَّةٌ",
      "en": "weak",
      "tr": "adhillatun",
      "ru": "слабы."
    },
    "aud": "003_123_006",
    "img": "/img/book.png"
  },
  {
    "id": 282,
    "text": {
      "ar": "أَلَنْ",
      "en": "Is it not",
      "tr": "alan",
      "ru": "«Разве не будет"
    },
    "aud": "003_124_004",
    "img": "/img/book.png"
  },
  {
    "id": 283,
    "text": {
      "ar": "يَكْفِيَكُمْ",
      "en": "enough for you",
      "tr": "yakfiyakum",
      "ru": "достаточно для вас"
    },
    "aud": "003_124_005",
    "img": "/img/book.png"
  },
  {
    "id": 284,
    "text": {
      "ar": "يُمِدَّكُمْ",
      "en": "reinforces you",
      "tr": "yumiddakum",
      "ru": "окажет вам поддержку"
    },
    "aud": "003_124_007",
    "img": "/img/book.png"
  },
  {
    "id": 285,
    "text": {
      "ar": "بِثَلَاثَةِ",
      "en": "with three",
      "tr": "bithalāthati",
      "ru": "тремя"
    },
    "aud": "003_124_009",
    "img": "/img/book.png"
  },
  {
    "id": 286,
    "text": {
      "ar": "ءَالَافٍ",
      "en": "thousand[s]",
      "tr": "ālāfin",
      "ru": "тысячами"
    },
    "aud": "003_124_010",
    "img": "/img/book.png"
  },
  {
    "id": 287,
    "text": {
      "ar": "مُنْزَلِينَ",
      "en": "[the ones] sent down",
      "tr": "munzalīna",
      "ru": "ниспосылаемыми?»"
    },
    "aud": "003_124_013",
    "img": "/img/book.png"
  },
  {
    "id": 288,
    "text": {
      "ar": "وَيَأْتُوكُمْ",
      "en": "and they come upon you",
      "tr": "wayatūkum",
      "ru": "и придут они на вас"
    },
    "aud": "003_125_005",
    "img": "/img/book.png"
  },
  {
    "id": 289,
    "text": {
      "ar": "فَوْرِهِمْ",
      "en": "suddenly",
      "tr": "fawrihim",
      "ru": "их внезапности"
    },
    "aud": "003_125_007",
    "img": "/img/book.png"
  },
  {
    "id": 290,
    "text": {
      "ar": "يُمْدِدْكُمْ",
      "en": "will reinforce you",
      "tr": "yum'did'kum",
      "ru": "поможет вам"
    },
    "aud": "003_125_009",
    "img": "/img/book.png"
  },
  {
    "id": 291,
    "text": {
      "ar": "بِخَمْسَةِ",
      "en": "with five",
      "tr": "bikhamsati",
      "ru": "пятью"
    },
    "aud": "003_125_011",
    "img": "/img/book.png"
  },
  {
    "id": 292,
    "text": {
      "ar": "مُسَوِّمِينَ",
      "en": "[the ones] having marks",
      "tr": "musawwimīna",
      "ru": "меченых."
    },
    "aud": "003_125_015",
    "img": "/img/book.png"
  },
  {
    "id": 293,
    "text": {
      "ar": "لِيَقْطَعَ",
      "en": "That He may cut off",
      "tr": "liyaqṭaʿa",
      "ru": "Чтобы Он отсёк"
    },
    "aud": "003_127_001",
    "img": "/img/book.png"
  },
  {
    "id": 294,
    "text": {
      "ar": "طَرَفًا",
      "en": "a part",
      "tr": "ṭarafan",
      "ru": "одну часть"
    },
    "aud": "003_127_002",
    "img": "/img/book.png"
  },
  {
    "id": 295,
    "text": {
      "ar": "يَكْبِتَهُمْ",
      "en": "suppress them",
      "tr": "yakbitahum",
      "ru": "(чтобы) разгромил Он их,"
    },
    "aud": "003_127_007",
    "img": "/img/book.png"
  },
  {
    "id": 296,
    "text": {
      "ar": "فَيَنْقَلِبُوا",
      "en": "so (that) they turn back",
      "tr": "fayanqalibū",
      "ru": "(так что) они вернутся"
    },
    "aud": "003_127_008",
    "img": "/img/book.png"
  },
  {
    "id": 297,
    "text": {
      "ar": "خَائِبِينَ",
      "en": "disappointed",
      "tr": "khāibīna",
      "ru": "безуспешными."
    },
    "aud": "003_127_009",
    "img": "/img/book.png"
  },
  {
    "id": 298,
    "text": {
      "ar": "أَضْعَافًا",
      "en": "doubled",
      "tr": "aḍʿāfan",
      "ru": "увеличенным"
    },
    "aud": "003_130_007",
    "img": "/img/book.png"
  },
  {
    "id": 299,
    "text": {
      "ar": "مُضَاعَفَةً",
      "en": "multiplied",
      "tr": "muḍāʿafatan",
      "ru": "многократно"
    },
    "aud": "003_130_008",
    "img": "/img/book.png"
  },
  {
    "id": 300,
    "text": {
      "ar": "وَسَارِعُوا",
      "en": "And hasten",
      "tr": "wasāriʿū",
      "ru": "И стремитесь"
    },
    "aud": "003_133_001",
    "img": "/img/book.png"
  },
  {
    "id": 301,
    "text": {
      "ar": "السَّرَّاءِ",
      "en": "[the] ease",
      "tr": "l-sarāi",
      "ru": "радости"
    },
    "aud": "003_134_004",
    "img": "/img/book.png"
  },
  {
    "id": 302,
    "text": {
      "ar": "وَالْكَاظِمِينَ",
      "en": "and those who restrain",
      "tr": "wal-kāẓimīna",
      "ru": "и (они) сдерживающие"
    },
    "aud": "003_134_006",
    "img": "/img/book.png"
  },
  {
    "id": 303,
    "text": {
      "ar": "الْغَيْظَ",
      "en": "the anger",
      "tr": "l-ghayẓa",
      "ru": "гнев"
    },
    "aud": "003_134_007",
    "img": "/img/book.png"
  },
  {
    "id": 304,
    "text": {
      "ar": "وَالْعَافِينَ",
      "en": "and those who pardon",
      "tr": "wal-ʿāfīna",
      "ru": "и (они) прощающие"
    },
    "aud": "003_134_008",
    "img": "/img/book.png"
  },
  {
    "id": 305,
    "text": {
      "ar": "ذَكَرُوا",
      "en": "they remember",
      "tr": "dhakarū",
      "ru": "вспоминают они"
    },
    "aud": "003_135_008",
    "img": "/img/book.png"
  },
  {
    "id": 306,
    "text": {
      "ar": "لِذُنُوبِهِمْ",
      "en": "for their sins",
      "tr": "lidhunūbihim",
      "ru": "своих грехов –"
    },
    "aud": "003_135_011",
    "img": "/img/book.png"
  },
  {
    "id": 307,
    "text": {
      "ar": "يُصِرُّوا",
      "en": "they persist",
      "tr": "yuṣirrū",
      "ru": "упорствуют"
    },
    "aud": "003_135_018",
    "img": "/img/book.png"
  },
  {
    "id": 308,
    "text": {
      "ar": "سُنَنٌ",
      "en": "situations",
      "tr": "sunanun",
      "ru": "примеры,"
    },
    "aud": "003_137_005",
    "img": "/img/book.png"
  },
  {
    "id": 309,
    "text": {
      "ar": "بَيَانٌ",
      "en": "(is) a declaration",
      "tr": "bayānun",
      "ru": "разъяснение"
    },
    "aud": "003_138_002",
    "img": "/img/book.png"
  },
  {
    "id": 310,
    "text": {
      "ar": "يَمْسَسْكُمْ",
      "en": "touched you",
      "tr": "yamsaskum",
      "ru": "коснулась вас"
    },
    "aud": "003_140_002",
    "img": "/img/book.png"
  },
  {
    "id": 311,
    "text": {
      "ar": "قَرْحٌ",
      "en": "a wound",
      "tr": "qarḥun",
      "ru": "(какая-нибудь) рана,"
    },
    "aud": "003_140_003",
    "img": "/img/book.png"
  },
  {
    "id": 312,
    "text": {
      "ar": "الْأَيَّامُ",
      "en": "[the] days",
      "tr": "l-ayāmu",
      "ru": "дни,"
    },
    "aud": "003_140_010",
    "img": "/img/book.png"
  },
  {
    "id": 313,
    "text": {
      "ar": "نُدَاوِلُهَا",
      "en": "We alternate them",
      "tr": "nudāwiluhā",
      "ru": "Мы сменяем их чередой"
    },
    "aud": "003_140_011",
    "img": "/img/book.png"
  },
  {
    "id": 314,
    "text": {
      "ar": "وَيَتَّخِذَ",
      "en": "and take",
      "tr": "wayattakhidha",
      "ru": "и взял Он"
    },
    "aud": "003_140_018",
    "img": "/img/book.png"
  },
  {
    "id": 315,
    "text": {
      "ar": "وَلِيُمَحِّصَ",
      "en": "And so that may purify",
      "tr": "waliyumaḥḥiṣa",
      "ru": "И чтобы очистил"
    },
    "aud": "003_141_001",
    "img": "/img/book.png"
  },
  {
    "id": 316,
    "text": {
      "ar": "وَيَمْحَقَ",
      "en": "and destroy",
      "tr": "wayamḥaqa",
      "ru": "и уничтожил Он"
    },
    "aud": "003_141_005",
    "img": "/img/book.png"
  },
  {
    "id": 317,
    "text": {
      "ar": "تَمَنَّوْنَ",
      "en": "wish",
      "tr": "tamannawna",
      "ru": "[[MISSING]]"
    },
    "aud": "003_143_003",
    "img": "/img/book.png"
  },
  {
    "id": 318,
    "text": {
      "ar": "تَلْقَوْهُ",
      "en": "you met it",
      "tr": "talqawhu",
      "ru": "встретили вы его [смерть]."
    },
    "aud": "003_143_008",
    "img": "/img/book.png"
  },
  {
    "id": 319,
    "text": {
      "ar": "رَأَيْتُمُوهُ",
      "en": "you have seen it",
      "tr": "ra-aytumūhu",
      "ru": "вы увидели его [смерть]"
    },
    "aud": "003_143_010",
    "img": "/img/book.png"
  },
  {
    "id": 320,
    "text": {
      "ar": "يَضُرَّ",
      "en": "will he harm",
      "tr": "yaḍurra",
      "ru": "навредит он"
    },
    "aud": "003_144_022",
    "img": "/img/book.png"
  },
  {
    "id": 321,
    "text": {
      "ar": "وَسَيَجْزِي",
      "en": "And will reward",
      "tr": "wasayajzī",
      "ru": "И вскоре воздаст"
    },
    "aud": "003_144_025",
    "img": "/img/book.png"
  },
  {
    "id": 322,
    "text": {
      "ar": "تَمُوتَ",
      "en": "he dies",
      "tr": "tamūta",
      "ru": "умерла она,"
    },
    "aud": "003_145_005",
    "img": "/img/book.png"
  },
  {
    "id": 323,
    "text": {
      "ar": "مُؤَجَّلًا",
      "en": "determined",
      "tr": "mu-ajjalan",
      "ru": "установленному."
    },
    "aud": "003_145_010",
    "img": "/img/book.png"
  },
  {
    "id": 324,
    "text": {
      "ar": "وَسَنَجْزِي",
      "en": "And We will reward",
      "tr": "wasanajzī",
      "ru": "И вскоре воздадим Мы"
    },
    "aud": "003_145_023",
    "img": "/img/book.png"
  },
  {
    "id": 325,
    "text": {
      "ar": "قَاتَلَ",
      "en": "fought",
      "tr": "qātala",
      "ru": "сражались"
    },
    "aud": "003_146_004",
    "img": "/img/book.png"
  },
  {
    "id": 326,
    "text": {
      "ar": "رِبِّيُّونَ",
      "en": "(were) religious scholars",
      "tr": "ribbiyyūna",
      "ru": "набожные верующие"
    },
    "aud": "003_146_006",
    "img": "/img/book.png"
  },
  {
    "id": 327,
    "text": {
      "ar": "وَهَنُوا",
      "en": "they lost heart",
      "tr": "wahanū",
      "ru": "падали они духом"
    },
    "aud": "003_146_009",
    "img": "/img/book.png"
  },
  {
    "id": 328,
    "text": {
      "ar": "ضَعُفُوا",
      "en": "they weakened",
      "tr": "ḍaʿufū",
      "ru": "проявляли они слабости"
    },
    "aud": "003_146_016",
    "img": "/img/book.png"
  },
  {
    "id": 329,
    "text": {
      "ar": "قَوْلَهُمْ",
      "en": "their words",
      "tr": "qawlahum",
      "ru": "речью их,"
    },
    "aud": "003_147_003",
    "img": "/img/book.png"
  },
  {
    "id": 330,
    "text": {
      "ar": "وَإِسْرَافَنَا",
      "en": "and our excesses",
      "tr": "wa-is'rāfanā",
      "ru": "и чрезмерность нашу"
    },
    "aud": "003_147_011",
    "img": "/img/book.png"
  },
  {
    "id": 331,
    "text": {
      "ar": "وَثَبِّتْ",
      "en": "and make firm",
      "tr": "wathabbit",
      "ru": "и укрепи"
    },
    "aud": "003_147_014",
    "img": "/img/book.png"
  },
  {
    "id": 332,
    "text": {
      "ar": "أَقْدَامَنَا",
      "en": "our feet",
      "tr": "aqdāmanā",
      "ru": "наши стопы"
    },
    "aud": "003_147_015",
    "img": "/img/book.png"
  },
  {
    "id": 333,
    "text": {
      "ar": "وَانْصُرْنَا",
      "en": "and give us victory",
      "tr": "wa-unṣur'nā",
      "ru": "и помоги нам в победе"
    },
    "aud": "003_147_016",
    "img": "/img/book.png"
  },
  {
    "id": 334,
    "text": {
      "ar": "فَءَاتَاهُمُ",
      "en": "So gave them",
      "tr": "faātāhumu",
      "ru": "И (затем) даровал им"
    },
    "aud": "003_148_001",
    "img": "/img/book.png"
  },
  {
    "id": 335,
    "text": {
      "ar": "ثَوَابِ",
      "en": "reward",
      "tr": "thawābi",
      "ru": "награду"
    },
    "aud": "003_148_006",
    "img": "/img/book.png"
  },
  {
    "id": 336,
    "text": {
      "ar": "النَّاصِرِينَ",
      "en": "(of) the Helpers",
      "tr": "l-nāṣirīna",
      "ru": "из помощников!"
    },
    "aud": "003_150_006",
    "img": "/img/book.png"
  },
  {
    "id": 337,
    "text": {
      "ar": "صَدَقَكُمُ",
      "en": "fulfilled to you",
      "tr": "ṣadaqakumu",
      "ru": "оправдал вам"
    },
    "aud": "003_152_002",
    "img": "/img/book.png"
  },
  {
    "id": 338,
    "text": {
      "ar": "تَحُسُّونَهُمْ",
      "en": "you were killing them",
      "tr": "taḥussūnahum",
      "ru": "вы уничтожали их"
    },
    "aud": "003_152_006",
    "img": "/img/book.png"
  },
  {
    "id": 339,
    "text": {
      "ar": "فَشِلْتُمْ",
      "en": "you lost courage",
      "tr": "fashil'tum",
      "ru": "ослабли вы духом,"
    },
    "aud": "003_152_010",
    "img": "/img/book.png"
  },
  {
    "id": 340,
    "text": {
      "ar": "وَتَنَازَعْتُمْ",
      "en": "and you fell into dispute",
      "tr": "watanāzaʿtum",
      "ru": "и стали вы препираться"
    },
    "aud": "003_152_011",
    "img": "/img/book.png"
  },
  {
    "id": 341,
    "text": {
      "ar": "وَعَصَيْتُمْ",
      "en": "and you disobeyed",
      "tr": "waʿaṣaytum",
      "ru": "и ослушались вы"
    },
    "aud": "003_152_014",
    "img": "/img/book.png"
  },
  {
    "id": 342,
    "text": {
      "ar": "صَرَفَكُمْ",
      "en": "He diverted you",
      "tr": "ṣarafakum",
      "ru": "отвернул Он вас"
    },
    "aud": "003_152_030",
    "img": "/img/book.png"
  },
  {
    "id": 343,
    "text": {
      "ar": "لِيَبْتَلِيَكُمْ",
      "en": "so that He may test you",
      "tr": "liyabtaliyakum",
      "ru": "чтобы испытать вас."
    },
    "aud": "003_152_032",
    "img": "/img/book.png"
  },
  {
    "id": 344,
    "text": {
      "ar": "تُصْعِدُونَ",
      "en": "you were running uphill",
      "tr": "tuṣ'ʿidūna",
      "ru": "поднимаетесь вы"
    },
    "aud": "003_153_002",
    "img": "/img/book.png"
  },
  {
    "id": 345,
    "text": {
      "ar": "تَلْوُونَ",
      "en": "casting a glance",
      "tr": "talwūna",
      "ru": "поворачиваетесь"
    },
    "aud": "003_153_004",
    "img": "/img/book.png"
  },
  {
    "id": 346,
    "text": {
      "ar": "أُخْرَاكُمْ",
      "en": "(from) behind you",
      "tr": "ukh'rākum",
      "ru": "последних ваших (рядах)."
    },
    "aud": "003_153_010",
    "img": "/img/book.png"
  },
  {
    "id": 347,
    "text": {
      "ar": "فَأَثَابَكُمْ",
      "en": "So (He) repaid you",
      "tr": "fa-athābakum",
      "ru": "И (затем) отплатил Он вам"
    },
    "aud": "003_153_011",
    "img": "/img/book.png"
  },
  {
    "id": 348,
    "text": {
      "ar": "غَمًّا",
      "en": "(with) distress",
      "tr": "ghamman",
      "ru": "огорчением"
    },
    "aud": "003_153_012",
    "img": "/img/book.png"
  },
  {
    "id": 349,
    "text": {
      "ar": "بِغَمٍّ",
      "en": "on distress",
      "tr": "bighammin",
      "ru": "за огорчением,"
    },
    "aud": "003_153_013",
    "img": "/img/book.png"
  },
  {
    "id": 350,
    "text": {
      "ar": "نُعَاسًا",
      "en": "slumber",
      "tr": "nuʿāsan",
      "ru": "дремоту,"
    },
    "aud": "003_154_008",
    "img": "/img/book.png"
  },
  {
    "id": 351,
    "text": {
      "ar": "أَهَمَّتْهُمْ",
      "en": "worried [them]",
      "tr": "ahammathum",
      "ru": "озаботили их"
    },
    "aud": "003_154_014",
    "img": "/img/book.png"
  },
  {
    "id": 352,
    "text": {
      "ar": "كُلَّهُ",
      "en": "all (of) it",
      "tr": "kullahu",
      "ru": "всё оно"
    },
    "aud": "003_154_032",
    "img": "/img/book.png"
  },
  {
    "id": 353,
    "text": {
      "ar": "يُبْدُونَ",
      "en": "they reveal",
      "tr": "yub'dūna",
      "ru": "открывают"
    },
    "aud": "003_154_039",
    "img": "/img/book.png"
  },
  {
    "id": 354,
    "text": {
      "ar": "قُتِلْنَا",
      "en": "we would have been killed",
      "tr": "qutil'nā",
      "ru": "были (бы) мы убиты"
    },
    "aud": "003_154_049",
    "img": "/img/book.png"
  },
  {
    "id": 355,
    "text": {
      "ar": "لَبَرَزَ",
      "en": "surely (would have) come out",
      "tr": "labaraza",
      "ru": "(то) однозначно, вышли бы"
    },
    "aud": "003_154_056",
    "img": "/img/book.png"
  },
  {
    "id": 356,
    "text": {
      "ar": "الْقَتْلُ",
      "en": "[the] death",
      "tr": "l-qatlu",
      "ru": "убиение"
    },
    "aud": "003_154_060",
    "img": "/img/book.png"
  },
  {
    "id": 357,
    "text": {
      "ar": "مَضَاجِعِهِمْ",
      "en": "their places of death",
      "tr": "maḍājiʿihim",
      "ru": "местам их лежания [смерти]."
    },
    "aud": "003_154_062",
    "img": "/img/book.png"
  },
  {
    "id": 358,
    "text": {
      "ar": "وَلِيَبْتَلِيَ",
      "en": "And that might test",
      "tr": "waliyabtaliya",
      "ru": "И чтобы испытал"
    },
    "aud": "003_154_063",
    "img": "/img/book.png"
  },
  {
    "id": 359,
    "text": {
      "ar": "اسْتَزَلَّهُمُ",
      "en": "made them slip",
      "tr": "is'tazallahumu",
      "ru": "заставил споткнуться их"
    },
    "aud": "003_155_009",
    "img": "/img/book.png"
  },
  {
    "id": 360,
    "text": {
      "ar": "غُزًّى",
      "en": "fighting",
      "tr": "ghuzzan",
      "ru": "в походе:"
    },
    "aud": "003_156_016",
    "img": "/img/book.png"
  },
  {
    "id": 361,
    "text": {
      "ar": "قُتِلْتُمْ",
      "en": "you are killed",
      "tr": "qutil'tum",
      "ru": "будете вы убиты"
    },
    "aud": "003_157_002",
    "img": "/img/book.png"
  },
  {
    "id": 362,
    "text": {
      "ar": "مُتُّمْ",
      "en": "die[d]",
      "tr": "muttum",
      "ru": "умрёте,"
    },
    "aud": "003_157_007",
    "img": "/img/book.png"
  },
  {
    "id": 363,
    "text": {
      "ar": "لَمَغْفِرَةٌ",
      "en": "certainly forgiveness",
      "tr": "lamaghfiratun",
      "ru": "(то) однозначно, прощение"
    },
    "aud": "003_157_008",
    "img": "/img/book.png"
  },
  {
    "id": 364,
    "text": {
      "ar": "لِنْتَ",
      "en": "you dealt gently",
      "tr": "linta",
      "ru": "был ты мягким"
    },
    "aud": "003_159_005",
    "img": "/img/book.png"
  },
  {
    "id": 365,
    "text": {
      "ar": "فَظًّا",
      "en": "rude",
      "tr": "faẓẓan",
      "ru": "грубым,"
    },
    "aud": "003_159_009",
    "img": "/img/book.png"
  },
  {
    "id": 366,
    "text": {
      "ar": "غَلِيظَ",
      "en": "(and) harsh",
      "tr": "ghalīẓa",
      "ru": "(с) жестким"
    },
    "aud": "003_159_010",
    "img": "/img/book.png"
  },
  {
    "id": 367,
    "text": {
      "ar": "الْقَلْبِ",
      "en": "(at) [the] heart",
      "tr": "l-qalbi",
      "ru": "сердцем,"
    },
    "aud": "003_159_011",
    "img": "/img/book.png"
  },
  {
    "id": 368,
    "text": {
      "ar": "لَانْفَضُّوا",
      "en": "surely they (would have) dispersed",
      "tr": "la-infaḍḍū",
      "ru": "однозначно, разошлись бы они"
    },
    "aud": "003_159_012",
    "img": "/img/book.png"
  },
  {
    "id": 369,
    "text": {
      "ar": "حَوْلِكَ",
      "en": "around you",
      "tr": "ḥawlika",
      "ru": "(вокруг) тебя."
    },
    "aud": "003_159_014",
    "img": "/img/book.png"
  },
  {
    "id": 370,
    "text": {
      "ar": "وَشَاوِرْهُمْ",
      "en": "and consult them",
      "tr": "washāwir'hum",
      "ru": "и советуйся с ними"
    },
    "aud": "003_159_019",
    "img": "/img/book.png"
  },
  {
    "id": 371,
    "text": {
      "ar": "عَزَمْتَ",
      "en": "you have decided",
      "tr": "ʿazamta",
      "ru": "ты решился,"
    },
    "aud": "003_159_023",
    "img": "/img/book.png"
  },
  {
    "id": 372,
    "text": {
      "ar": "الْمُتَوَكِّلِينَ",
      "en": "the ones who put trust (in Him)",
      "tr": "l-mutawakilīna",
      "ru": "уповающих!"
    },
    "aud": "003_159_030",
    "img": "/img/book.png"
  },
  {
    "id": 373,
    "text": {
      "ar": "يَنْصُرْكُمُ",
      "en": "helps you",
      "tr": "yanṣur'kumu",
      "ru": "окажет помощь вам"
    },
    "aud": "003_160_002",
    "img": "/img/book.png"
  },
  {
    "id": 374,
    "text": {
      "ar": "يَخْذُلْكُمْ",
      "en": "He forsakes you",
      "tr": "yakhdhul'kum",
      "ru": "оставит Он вас без помощи,"
    },
    "aud": "003_160_008",
    "img": "/img/book.png"
  },
  {
    "id": 375,
    "text": {
      "ar": "يَغُلَّ",
      "en": "he defrauds",
      "tr": "yaghulla",
      "ru": "он обманом присвоил (что-то),"
    },
    "aud": "003_161_005",
    "img": "/img/book.png"
  },
  {
    "id": 376,
    "text": {
      "ar": "يَغْلُلْ",
      "en": "defrauds",
      "tr": "yaghlul",
      "ru": "обманом присвоит,"
    },
    "aud": "003_161_007",
    "img": "/img/book.png"
  },
  {
    "id": 377,
    "text": {
      "ar": "غَلَّ",
      "en": "he had defrauded",
      "tr": "ghalla",
      "ru": "присвоил,"
    },
    "aud": "003_161_010",
    "img": "/img/book.png"
  },
  {
    "id": 378,
    "text": {
      "ar": "تُوَفَّى",
      "en": "is repaid in full",
      "tr": "tuwaffā",
      "ru": "будет уплачено сполна"
    },
    "aud": "003_161_014",
    "img": "/img/book.png"
  },
  {
    "id": 379,
    "text": {
      "ar": "أَفَمَنِ",
      "en": "So is (the one) who",
      "tr": "afamani",
      "ru": "Разве же тот, кто"
    },
    "aud": "003_162_001",
    "img": "/img/book.png"
  },
  {
    "id": 380,
    "text": {
      "ar": "رِضْوَانَ",
      "en": "(the) pleasure",
      "tr": "riḍ'wāna",
      "ru": "благоволением"
    },
    "aud": "003_162_003",
    "img": "/img/book.png"
  },
  {
    "id": 381,
    "text": {
      "ar": "بِسَخَطٍ",
      "en": "on (himself) wrath",
      "tr": "bisakhaṭin",
      "ru": "с гневом"
    },
    "aud": "003_162_007",
    "img": "/img/book.png"
  },
  {
    "id": 382,
    "text": {
      "ar": "أَوَلَمَّا",
      "en": "Or",
      "tr": "awalammā",
      "ru": "И разве после того, как"
    },
    "aud": "003_165_001",
    "img": "/img/book.png"
  },
  {
    "id": 383,
    "text": {
      "ar": "أَصَبْتُمْ",
      "en": "surely",
      "tr": "aṣabtum",
      "ru": "причинили вы"
    },
    "aud": "003_165_005",
    "img": "/img/book.png"
  },
  {
    "id": 384,
    "text": {
      "ar": "مِثْلَيْهَا",
      "en": "you had struck (them)",
      "tr": "mith'layhā",
      "ru": "вдвое большее которого (несчастье),"
    },
    "aud": "003_165_006",
    "img": "/img/book.png"
  },
  {
    "id": 385,
    "text": {
      "ar": "ادْفَعُوا",
      "en": "defend",
      "tr": "id'faʿū",
      "ru": "отразите (врага от семей!)»"
    },
    "aud": "003_167_012",
    "img": "/img/book.png"
  },
  {
    "id": 386,
    "text": {
      "ar": "قِتَالًا",
      "en": "fighting",
      "tr": "qitālan",
      "ru": "сражение,"
    },
    "aud": "003_167_016",
    "img": "/img/book.png"
  },
  {
    "id": 387,
    "text": {
      "ar": "لَاتَّبَعْنَاكُمْ",
      "en": "certainly we (would have) followed you",
      "tr": "la-ittabaʿnākum",
      "ru": "то однозначно, последовали бы за вами."
    },
    "aud": "003_167_017",
    "img": "/img/book.png"
  },
  {
    "id": 388,
    "text": {
      "ar": "لِلْكُفْرِ",
      "en": "to disbelief",
      "tr": "lil'kuf'ri",
      "ru": "к неверию"
    },
    "aud": "003_167_019",
    "img": "/img/book.png"
  },
  {
    "id": 389,
    "text": {
      "ar": "بِأَفْواهِهِمْ",
      "en": "with their mouths",
      "tr": "bi-afwāhihim",
      "ru": "своими устами"
    },
    "aud": "003_167_025",
    "img": "/img/book.png"
  },
  {
    "id": 390,
    "text": {
      "ar": "وَقَعَدُوا",
      "en": "while they sat",
      "tr": "waqaʿadū",
      "ru": "в то время, как они отсиделись:"
    },
    "aud": "003_168_004",
    "img": "/img/book.png"
  },
  {
    "id": 391,
    "text": {
      "ar": "أَطَاعُونَا",
      "en": "they (had) obeyed us",
      "tr": "aṭāʿūnā",
      "ru": "повиновались они нам,"
    },
    "aud": "003_168_006",
    "img": "/img/book.png"
  },
  {
    "id": 392,
    "text": {
      "ar": "فَادْرَءُوا",
      "en": "Then avert",
      "tr": "fa-id'raū",
      "ru": "«Отвратите же"
    },
    "aud": "003_168_010",
    "img": "/img/book.png"
  },
  {
    "id": 393,
    "text": {
      "ar": "أَنْفُسِكُمُ",
      "en": "yourselves",
      "tr": "anfusikumu",
      "ru": "самих себя"
    },
    "aud": "003_168_012",
    "img": "/img/book.png"
  },
  {
    "id": 394,
    "text": {
      "ar": "أَمْوَاتًا",
      "en": "(as) dead",
      "tr": "amwātan",
      "ru": "умершими."
    },
    "aud": "003_169_008",
    "img": "/img/book.png"
  },
  {
    "id": 395,
    "text": {
      "ar": "أَحْيَاءٌ",
      "en": "They are alive",
      "tr": "aḥyāon",
      "ru": "живые!"
    },
    "aud": "003_169_010",
    "img": "/img/book.png"
  },
  {
    "id": 396,
    "text": {
      "ar": "فَرِحِينَ",
      "en": "Rejoicing",
      "tr": "fariḥīna",
      "ru": "радуясь"
    },
    "aud": "003_170_001",
    "img": "/img/book.png"
  },
  {
    "id": 397,
    "text": {
      "ar": "وَيَسْتَبْشِرُونَ",
      "en": "and they receive good tidings",
      "tr": "wayastabshirūna",
      "ru": "и ликуя"
    },
    "aud": "003_170_007",
    "img": "/img/book.png"
  },
  {
    "id": 398,
    "text": {
      "ar": "بِنِعْمَةٍ",
      "en": "of Favor",
      "tr": "biniʿ'matin",
      "ru": "о благодати"
    },
    "aud": "003_171_002",
    "img": "/img/book.png"
  },
  {
    "id": 399,
    "text": {
      "ar": "الْقَرْحُ",
      "en": "the injury",
      "tr": "l-qarḥu",
      "ru": "раны."
    },
    "aud": "003_172_009",
    "img": "/img/book.png"
  },
  {
    "id": 400,
    "text": {
      "ar": "جَمَعُوا",
      "en": "gathered",
      "tr": "jamaʿū",
      "ru": "собрали (войско)"
    },
    "aud": "003_173_008",
    "img": "/img/book.png"
  },
  {
    "id": 401,
    "text": {
      "ar": "فَاخْشَوْهُمْ",
      "en": "so fear them",
      "tr": "fa-ikh'shawhum",
      "ru": "так бойтесь же их!»"
    },
    "aud": "003_173_010",
    "img": "/img/book.png"
  },
  {
    "id": 402,
    "text": {
      "ar": "فَزَادَهُمْ",
      "en": "But it increased them",
      "tr": "fazādahum",
      "ru": "Но (это) увеличило им"
    },
    "aud": "003_173_011",
    "img": "/img/book.png"
  },
  {
    "id": 403,
    "text": {
      "ar": "الْوَكِيلُ",
      "en": "[the] Disposer of affairs",
      "tr": "l-wakīlu",
      "ru": "покровитель!»"
    },
    "aud": "003_173_017",
    "img": "/img/book.png"
  },
  {
    "id": 404,
    "text": {
      "ar": "فَانْقَلَبُوا",
      "en": "So they returned",
      "tr": "fa-inqalabū",
      "ru": "И (затем) они вернулись"
    },
    "aud": "003_174_001",
    "img": "/img/book.png"
  },
  {
    "id": 405,
    "text": {
      "ar": "يَمْسَسْهُمْ",
      "en": "touched them",
      "tr": "yamsashum",
      "ru": "коснулось их"
    },
    "aud": "003_174_007",
    "img": "/img/book.png"
  },
  {
    "id": 406,
    "text": {
      "ar": "سُوءٌ",
      "en": "any harm",
      "tr": "sūon",
      "ru": "плохое,"
    },
    "aud": "003_174_008",
    "img": "/img/book.png"
  },
  {
    "id": 407,
    "text": {
      "ar": "تَخَافُوهُمْ",
      "en": "fear them",
      "tr": "takhāfūhum",
      "ru": "бойтесь же их,"
    },
    "aud": "003_175_007",
    "img": "/img/book.png"
  },
  {
    "id": 408,
    "text": {
      "ar": "وَخَافُونِ",
      "en": "but fear Me",
      "tr": "wakhāfūni",
      "ru": "а бойтесь Меня,"
    },
    "aud": "003_175_008",
    "img": "/img/book.png"
  },
  {
    "id": 409,
    "text": {
      "ar": "اشْتَرَوُا",
      "en": "(have) purchased",
      "tr": "ish'tarawū",
      "ru": "купили"
    },
    "aud": "003_177_003",
    "img": "/img/book.png"
  },
  {
    "id": 410,
    "text": {
      "ar": "نُمْلِي",
      "en": "We give respite",
      "tr": "num'lī",
      "ru": "даём Мы отсрочку"
    },
    "aud": "003_178_006",
    "img": "/img/book.png"
  },
  {
    "id": 411,
    "text": {
      "ar": "لِيَذَرَ",
      "en": "to leave",
      "tr": "liyadhara",
      "ru": "чтобы оставить"
    },
    "aud": "003_179_004",
    "img": "/img/book.png"
  },
  {
    "id": 412,
    "text": {
      "ar": "يَمِيزَ",
      "en": "He separates",
      "tr": "yamīza",
      "ru": "отличит Он"
    },
    "aud": "003_179_011",
    "img": "/img/book.png"
  },
  {
    "id": 413,
    "text": {
      "ar": "لِيُطْلِعَكُمْ",
      "en": "to inform you",
      "tr": "liyuṭ'liʿakum",
      "ru": "чтобы дать знать вам"
    },
    "aud": "003_179_018",
    "img": "/img/book.png"
  },
  {
    "id": 414,
    "text": {
      "ar": "رُسُلِهِ",
      "en": "His Messengers",
      "tr": "rusulihi",
      "ru": "Своих посланников,"
    },
    "aud": "003_179_025",
    "img": "/img/book.png"
  },
  {
    "id": 415,
    "text": {
      "ar": "فَلَكُمْ",
      "en": "then for you",
      "tr": "falakum",
      "ru": "то вам –"
    },
    "aud": "003_179_034",
    "img": "/img/book.png"
  },
  {
    "id": 416,
    "text": {
      "ar": "سَيُطَوَّقُونَ",
      "en": "Their necks will be encircled",
      "tr": "sayuṭawwaqūna",
      "ru": "Будут они обёрнуты"
    },
    "aud": "003_180_017",
    "img": "/img/book.png"
  },
  {
    "id": 417,
    "text": {
      "ar": "وَقَتْلَهُمُ",
      "en": "and their killing",
      "tr": "waqatlahumu",
      "ru": "и убийство ими"
    },
    "aud": "003_181_015",
    "img": "/img/book.png"
  },
  {
    "id": 418,
    "text": {
      "ar": "يَأْتِيَنَا",
      "en": "he brings to us",
      "tr": "yatiyanā",
      "ru": "явится он к нам"
    },
    "aud": "003_183_011",
    "img": "/img/book.png"
  },
  {
    "id": 419,
    "text": {
      "ar": "بِقُرْبَانٍ",
      "en": "a sacrifice",
      "tr": "biqur'bānin",
      "ru": "с жертвой,"
    },
    "aud": "003_183_012",
    "img": "/img/book.png"
  },
  {
    "id": 420,
    "text": {
      "ar": "تَأْكُلُهُ",
      "en": "consumes it",
      "tr": "takuluhu",
      "ru": "(которую) пожрёт"
    },
    "aud": "003_183_013",
    "img": "/img/book.png"
  },
  {
    "id": 421,
    "text": {
      "ar": "وَبِالَّذِي",
      "en": "and with what",
      "tr": "wabi-alladhī",
      "ru": "и с тем, о котором"
    },
    "aud": "003_183_022",
    "img": "/img/book.png"
  },
  {
    "id": 422,
    "text": {
      "ar": "قَتَلْتُمُوهُمْ",
      "en": "you killed them",
      "tr": "qataltumūhum",
      "ru": "вы убили их,"
    },
    "aud": "003_183_025",
    "img": "/img/book.png"
  },
  {
    "id": 423,
    "text": {
      "ar": "كُذِّبَ",
      "en": "were rejected",
      "tr": "kudhiba",
      "ru": "считали лжецами"
    },
    "aud": "003_184_004",
    "img": "/img/book.png"
  },
  {
    "id": 424,
    "text": {
      "ar": "تُوَفَّوْنَ",
      "en": "you will be paid in full",
      "tr": "tuwaffawna",
      "ru": "будут сполна даны вам"
    },
    "aud": "003_185_006",
    "img": "/img/book.png"
  },
  {
    "id": 425,
    "text": {
      "ar": "زُحْزِحَ",
      "en": "is drawn away",
      "tr": "zuḥ'ziḥa",
      "ru": "будет отдалён"
    },
    "aud": "003_185_011",
    "img": "/img/book.png"
  },
  {
    "id": 426,
    "text": {
      "ar": "لَتُبْلَوُنَّ",
      "en": "You will certainly be tested",
      "tr": "latub'lawunna",
      "ru": "(Клянусь Я, что) непременно будете вы испытаны"
    },
    "aud": "003_186_001",
    "img": "/img/book.png"
  },
  {
    "id": 427,
    "text": {
      "ar": "وَلَتَسْمَعُنَّ",
      "en": "And you will certainly hear",
      "tr": "walatasmaʿunna",
      "ru": "и (клянусь Я, что) непременно вы услышите"
    },
    "aud": "003_186_005",
    "img": "/img/book.png"
  },
  {
    "id": 428,
    "text": {
      "ar": "لَتُبَيِّنُنَّهُ",
      "en": "You certainly make it clear",
      "tr": "latubayyinunnahu",
      "ru": "«Непременно и однозначно, вы будете разъяснять его"
    },
    "aud": "003_187_008",
    "img": "/img/book.png"
  },
  {
    "id": 429,
    "text": {
      "ar": "تَكْتُمُونَهُ",
      "en": "conceal it",
      "tr": "taktumūnahu",
      "ru": "будете скрывать его»."
    },
    "aud": "003_187_011",
    "img": "/img/book.png"
  },
  {
    "id": 430,
    "text": {
      "ar": "فَنَبَذُوهُ",
      "en": "Then they threw it",
      "tr": "fanabadhūhu",
      "ru": "И (затем) они бросили это"
    },
    "aud": "003_187_012",
    "img": "/img/book.png"
  },
  {
    "id": 431,
    "text": {
      "ar": "وَاشْتَرَوْا",
      "en": "and they exchanged",
      "tr": "wa-ish'taraw",
      "ru": "и купили они"
    },
    "aud": "003_187_015",
    "img": "/img/book.png"
  },
  {
    "id": 432,
    "text": {
      "ar": "وَيُحِبُّونَ",
      "en": "and they love",
      "tr": "wayuḥibbūna",
      "ru": "и любят,"
    },
    "aud": "003_188_007",
    "img": "/img/book.png"
  },
  {
    "id": 433,
    "text": {
      "ar": "يُحْمَدُوا",
      "en": "they be praised",
      "tr": "yuḥ'madū",
      "ru": "хвалили их (досл. были они хвалимы)"
    },
    "aud": "003_188_009",
    "img": "/img/book.png"
  },
  {
    "id": 434,
    "text": {
      "ar": "تَحْسَبَنَّهُمْ",
      "en": "think (that) they",
      "tr": "taḥsabannahum",
      "ru": "считай ты (никак), что они"
    },
    "aud": "003_188_014",
    "img": "/img/book.png"
  },
  {
    "id": 435,
    "text": {
      "ar": "بِمَفَازَةٍ",
      "en": "(will) escape",
      "tr": "bimafāzatin",
      "ru": "(окажутся) с избавлением"
    },
    "aud": "003_188_015",
    "img": "/img/book.png"
  },
  {
    "id": 436,
    "text": {
      "ar": "جُنُوبِهِمْ",
      "en": "their sides",
      "tr": "junūbihim",
      "ru": "своих боках"
    },
    "aud": "003_191_007",
    "img": "/img/book.png"
  },
  {
    "id": 437,
    "text": {
      "ar": "وَيَتَفَكَّرُونَ",
      "en": "and they reflect",
      "tr": "wayatafakkarūna",
      "ru": "и размышляют"
    },
    "aud": "003_191_008",
    "img": "/img/book.png"
  },
  {
    "id": 438,
    "text": {
      "ar": "فَقِنَا",
      "en": "so save us",
      "tr": "faqinā",
      "ru": "Защити же нас"
    },
    "aud": "003_191_019",
    "img": "/img/book.png"
  },
  {
    "id": 439,
    "text": {
      "ar": "تُدْخِلِ",
      "en": "You admit",
      "tr": "tud'khili",
      "ru": "Ты введёшь"
    },
    "aud": "003_192_004",
    "img": "/img/book.png"
  },
  {
    "id": 440,
    "text": {
      "ar": "أَخْزَيْتَهُ",
      "en": "You (have) disgraced him",
      "tr": "akhzaytahu",
      "ru": "опозорил Ты того,"
    },
    "aud": "003_192_007",
    "img": "/img/book.png"
  },
  {
    "id": 441,
    "text": {
      "ar": "مُنَادِيًا",
      "en": "a caller",
      "tr": "munādiyan",
      "ru": "возглашающего,"
    },
    "aud": "003_193_004",
    "img": "/img/book.png"
  },
  {
    "id": 442,
    "text": {
      "ar": "يُنَادِي",
      "en": "calling",
      "tr": "yunādī",
      "ru": "(который) призвал"
    },
    "aud": "003_193_005",
    "img": "/img/book.png"
  },
  {
    "id": 443,
    "text": {
      "ar": "وَكَفِّرْ",
      "en": "and remove",
      "tr": "wakaffir",
      "ru": "и удали"
    },
    "aud": "003_193_015",
    "img": "/img/book.png"
  },
  {
    "id": 444,
    "text": {
      "ar": "سَيِّئَاتِنَا",
      "en": "our evil deeds",
      "tr": "sayyiātinā",
      "ru": "наши скверные деяния"
    },
    "aud": "003_193_017",
    "img": "/img/book.png"
  },
  {
    "id": 445,
    "text": {
      "ar": "وَءَاتِنَا",
      "en": "grant us",
      "tr": "waātinā",
      "ru": "И даруй нам"
    },
    "aud": "003_194_002",
    "img": "/img/book.png"
  },
  {
    "id": 446,
    "text": {
      "ar": "وَعَدْتَنَا",
      "en": "You promised us",
      "tr": "waʿadttanā",
      "ru": "обещал Ты нам"
    },
    "aud": "003_194_004",
    "img": "/img/book.png"
  },
  {
    "id": 447,
    "text": {
      "ar": "رُسُلِكَ",
      "en": "Your Messengers",
      "tr": "rusulika",
      "ru": "Своих посланников"
    },
    "aud": "003_194_006",
    "img": "/img/book.png"
  },
  {
    "id": 448,
    "text": {
      "ar": "تُخْزِنَا",
      "en": "disgrace us",
      "tr": "tukh'zinā",
      "ru": "позорь нас"
    },
    "aud": "003_194_008",
    "img": "/img/book.png"
  },
  {
    "id": 449,
    "text": {
      "ar": "تُخْلِفُ",
      "en": "break",
      "tr": "tukh'lifu",
      "ru": "нарушаешь"
    },
    "aud": "003_194_013",
    "img": "/img/book.png"
  },
  {
    "id": 450,
    "text": {
      "ar": "أُضِيعُ",
      "en": "(let go) waste",
      "tr": "uḍīʿu",
      "ru": "погублю Я"
    },
    "aud": "003_195_006",
    "img": "/img/book.png"
  },
  {
    "id": 451,
    "text": {
      "ar": "عَامِلٍ",
      "en": "(of the) doer",
      "tr": "ʿāmilin",
      "ru": "совершающего"
    },
    "aud": "003_195_008",
    "img": "/img/book.png"
  },
  {
    "id": 452,
    "text": {
      "ar": "وَأُخْرِجُوا",
      "en": "and were driven out",
      "tr": "wa-ukh'rijū",
      "ru": "и были изгнаны"
    },
    "aud": "003_195_019",
    "img": "/img/book.png"
  },
  {
    "id": 453,
    "text": {
      "ar": "وَقُتِلُوا",
      "en": "and were killed",
      "tr": "waqutilū",
      "ru": "и были убиты,"
    },
    "aud": "003_195_026",
    "img": "/img/book.png"
  },
  {
    "id": 454,
    "text": {
      "ar": "وَلَأُدْخِلَنَّهُمْ",
      "en": "and surely I will admit them",
      "tr": "wala-ud'khilannahum",
      "ru": "и (клянусь Я, что) непременно и введу их"
    },
    "aud": "003_195_030",
    "img": "/img/book.png"
  },
  {
    "id": 455,
    "text": {
      "ar": "الثَّوَابِ",
      "en": "reward",
      "tr": "l-thawābi",
      "ru": "вознаграждение!»"
    },
    "aud": "003_195_043",
    "img": "/img/book.png"
  },
  {
    "id": 456,
    "text": {
      "ar": "يَغُرَّنَّكَ",
      "en": "deceive you",
      "tr": "yaghurrannaka",
      "ru": "обманет тебя (никак)"
    },
    "aud": "003_196_002",
    "img": "/img/book.png"
  },
  {
    "id": 457,
    "text": {
      "ar": "تَقَلُّبُ",
      "en": "(the) movement",
      "tr": "taqallubu",
      "ru": "оборотливость"
    },
    "aud": "003_196_003",
    "img": "/img/book.png"
  },
  {
    "id": 458,
    "text": {
      "ar": "لِلْأَبْرَارِ",
      "en": "for the righteous",
      "tr": "lil'abrāri",
      "ru": "для благочестивых!"
    },
    "aud": "003_198_021",
    "img": "/img/book.png"
  },
  {
    "id": 459,
    "text": {
      "ar": "اصْبِرُوا",
      "en": "Be steadfast",
      "tr": "iṣ'birū",
      "ru": "Проявляйте терпение,"
    },
    "aud": "003_200_004",
    "img": "/img/book.png"
  },
  {
    "id": 460,
    "text": {
      "ar": "وَصَابِرُوا",
      "en": "and [be] patient",
      "tr": "waṣābirū",
      "ru": "и старайтесь превзойти других в терпении"
    },
    "aud": "003_200_005",
    "img": "/img/book.png"
  },
  {
    "id": 461,
    "text": {
      "ar": "وَرَابِطُوا",
      "en": "and [be] constant",
      "tr": "warābiṭū",
      "ru": "и охраняйте границы"
    },
    "aud": "003_200_006",
    "img": "/img/book.png"
  }
]